{
"C20720170927T071703001@import": {
        "ID"        :"C20720170927T071703001@import",
        "apogee"    :"4TBI904U",
        "acronym"   :"S09::DEA",
        "date_start":"2018-01-12T08:00",
        "date_end"  :"2018-01-12T11:00",
        "lecturer"  :"Desbarats P",
        "location"  :"None::None@Room_000",
        "group"     :"All",
        "type"      :"Cours+TD",
        "year"      :"2",
        "tracks"    :"0x07",
        "comment"   :"Imported from .ics - Wed Sep 27 2017 09:17:03 GMT+0200 (CEST)"},
"C20720170927T071703002@import": {
        "ID"        :"C20720170927T071703002@import",
        "apogee"    :"4TBI904U",
        "acronym"   :"S09::DEA",
        "date_start":"2017-11-10T08:00",
        "date_end"  :"2017-11-10T11:00",
        "lecturer"  :"Desbarats P",
        "location"  :"Talence::A29-CREMI@Room_207",
        "group"     :"All",
        "type"      :"Cours+TD",
        "year"      :"2",
        "tracks"    :"0x07",
        "comment"   :"Imported from .ics - Wed Sep 27 2017 09:17:03 GMT+0200 (CEST)"},
"C20720170927T071703003@import": {
        "ID"        :"C20720170927T071703003@import",
        "apogee"    :"4TBI904U",
        "acronym"   :"S09::DEA",
        "date_start":"2017-11-10T08:00",
        "date_end"  :"2017-11-10T11:00",
        "lecturer"  :"Desbarats P",
        "location"  :"Talence::A29-CREMI@Room_207",
        "group"     :"All",
        "type"      :"Cours+TD",
        "year"      :"2",
        "tracks"    :"0x07",
        "comment"   :"Imported from .ics - Wed Sep 27 2017 09:17:03 GMT+0200 (CEST)"},
"C20720170927T071703004@import": {
        "ID"        :"C20720170927T071703004@import",
        "apogee"    :"4TBI904U",
        "acronym"   :"S09::DEA",
        "date_start":"2017-11-17T08:00",
        "date_end"  :"2017-11-17T11:00",
        "lecturer"  :"Desbarats P",
        "location"  :"Talence::A29-CREMI@Room_207",
        "group"     :"All",
        "type"      :"Cours+TD",
        "year"      :"2",
        "tracks"    :"0x07",
        "comment"   :"Imported from .ics - Wed Sep 27 2017 09:17:03 GMT+0200 (CEST)"},
"C20720170927T071703005@import": {
        "ID"        :"C20720170927T071703005@import",
        "apogee"    :"4TBI904U",
        "acronym"   :"S09::DEA",
        "date_start":"2017-11-24T08:00",
        "date_end"  :"2017-11-24T11:00",
        "lecturer"  :"Desbarats P",
        "location"  :"Talence::A29-CREMI@Room_207",
        "group"     :"All",
        "type"      :"Cours+TD",
        "year"      :"2",
        "tracks"    :"0x07",
        "comment"   :"Imported from .ics - Wed Sep 27 2017 09:17:03 GMT+0200 (CEST)"},
"C20720170927T071703006@import": {
        "ID"        :"C20720170927T071703006@import",
        "apogee"    :"4TBI904U",
        "acronym"   :"S09::DEA",
        "date_start":"2017-12-01T08:00",
        "date_end"  :"2017-12-01T11:00",
        "lecturer"  :"Desbarats P",
        "location"  :"Talence::A29-CREMI@Room_207",
        "group"     :"All",
        "type"      :"Cours+TD",
        "year"      :"2",
        "tracks"    :"0x07",
        "comment"   :"Imported from .ics - Wed Sep 27 2017 09:17:03 GMT+0200 (CEST)"},
"C20720170927T071703007@import": {
        "ID"        :"C20720170927T071703007@import",
        "apogee"    :"4TBI904U",
        "acronym"   :"S09::DEA",
        "date_start":"2017-10-06T08:00",
        "date_end"  :"2017-10-06T11:00",
        "lecturer"  :"Desbarats P",
        "location"  :"Talence::A29-CREMI@Room_207",
        "group"     :"All",
        "type"      :"Cours+TD",
        "year"      :"2",
        "tracks"    :"0x07",
        "comment"   :"Imported from .ics - Wed Sep 27 2017 09:17:03 GMT+0200 (CEST)"},
"C20720170927T071703008@import": {
        "ID"        :"C20720170927T071703008@import",
        "apogee"    :"4TBI904U",
        "acronym"   :"S09::DEA",
        "date_start":"2017-10-13T08:00",
        "date_end"  :"2017-10-13T11:00",
        "lecturer"  :"Desbarats P",
        "location"  :"Talence::A29-CREMI@Room_207",
        "group"     :"All",
        "type"      :"Cours+TD",
        "year"      :"2",
        "tracks"    :"0x07",
        "comment"   :"Imported from .ics - Wed Sep 27 2017 09:17:03 GMT+0200 (CEST)"},
"C20720170927T071703009@import": {
        "ID"        :"C20720170927T071703009@import",
        "apogee"    :"4TBI904U",
        "acronym"   :"S09::DEA",
        "date_start":"2017-10-20T08:00",
        "date_end"  :"2017-10-20T11:00",
        "lecturer"  :"Desbarats P",
        "location"  :"Talence::A29-CREMI@Room_207",
        "group"     :"All",
        "type"      :"Cours+TD",
        "year"      :"2",
        "tracks"    :"0x07",
        "comment"   :"Imported from .ics - Wed Sep 27 2017 09:17:03 GMT+0200 (CEST)"},
"C20720170927T071703010@import": {
        "ID"        :"C20720170927T071703010@import",
        "apogee"    :"4TBI904U",
        "acronym"   :"S09::DEA",
        "date_start":"2017-10-27T08:00",
        "date_end"  :"2017-10-27T11:00",
        "lecturer"  :"Desbarats P",
        "location"  :"Talence::A29-CREMI@Room_207",
        "group"     :"All",
        "type"      :"Cours+TD",
        "year"      :"2",
        "tracks"    :"0x07",
        "comment"   :"Imported from .ics - Wed Sep 27 2017 09:17:03 GMT+0200 (CEST)"},
"C26020170927T071703011@import": {
        "ID"        :"C26020170927T071703011@import",
        "apogee"    :"4TBE902U",
        "acronym"   :"S09::EvoComm",
        "date_start":"2017-09-06T09:30",
        "date_end"  :"2017-09-06T12:00",
        "lecturer"  :"Fi&eacute;vet V",
        "location"  :"Talence::B4@Room_A2",
        "group"     :"All",
        "type"      :"Cours",
        "year"      :"2",
        "tracks"    :"0x60",
        "comment"   :"Imported from .ics - Wed Sep 27 2017 09:17:03 GMT+0200 (CEST)"},
"C26020170927T071703012@import": {
        "ID"        :"C26020170927T071703012@import",
        "apogee"    :"4TBE902U",
        "acronym"   :"S09::EvoComm",
        "date_start":"2017-10-04T14:00",
        "date_end"  :"2017-10-04T17:00",
        "lecturer"  :"Fi&eacute;vet V",
        "location"  :"None::None@Room_000",
        "group"     :"All",
        "type"      :"Cours",
        "year"      :"2",
        "tracks"    :"0x60",
        "comment"   :"Imported from .ics - Wed Sep 27 2017 09:17:03 GMT+0200 (CEST)"},
"C26020170927T071703013@import": {
        "ID"        :"C26020170927T071703013@import",
        "apogee"    :"4TBE902U",
        "acronym"   :"S09::EvoComm",
        "date_start":"2017-10-11T14:00",
        "date_end"  :"2017-10-11T17:00",
        "lecturer"  :"Fi&eacute;vet V",
        "location"  :"None::None@Room_000",
        "group"     :"All",
        "type"      :"Cours",
        "year"      :"2",
        "tracks"    :"0x60",
        "comment"   :"Imported from .ics - Wed Sep 27 2017 09:17:03 GMT+0200 (CEST)"},
"C26020170927T071703014@import": {
        "ID"        :"C26020170927T071703014@import",
        "apogee"    :"4TBE902U",
        "acronym"   :"S09::EvoComm",
        "date_start":"2017-10-25T09:00",
        "date_end"  :"2017-10-25T12:00",
        "lecturer"  :"Fi&eacute;vet V",
        "location"  :"None::None@Room_000",
        "group"     :"All",
        "type"      :"Cours",
        "year"      :"2",
        "tracks"    :"0x60",
        "comment"   :"Imported from .ics - Wed Sep 27 2017 09:17:03 GMT+0200 (CEST)"},
"C26020170927T071703015@import": {
        "ID"        :"C26020170927T071703015@import",
        "apogee"    :"4TBE902U",
        "acronym"   :"S09::EvoComm",
        "date_start":"2017-11-08T09:00",
        "date_end"  :"2017-11-08T12:00",
        "lecturer"  :"Fi&eacute;vet V",
        "location"  :"None::None@Room_000",
        "group"     :"All",
        "type"      :"Cours",
        "year"      :"2",
        "tracks"    :"0x60",
        "comment"   :"Imported from .ics - Wed Sep 27 2017 09:17:03 GMT+0200 (CEST)"},
"C26020170927T071703016@import": {
        "ID"        :"C26020170927T071703016@import",
        "apogee"    :"4TBE902U",
        "acronym"   :"S09::EvoComm",
        "date_start":"2017-11-15T09:00",
        "date_end"  :"2017-11-15T12:00",
        "lecturer"  :"Fi&eacute;vet V",
        "location"  :"None::None@Room_000",
        "group"     :"All",
        "type"      :"Cours",
        "year"      :"2",
        "tracks"    :"0x60",
        "comment"   :"Imported from .ics - Wed Sep 27 2017 09:17:03 GMT+0200 (CEST)"},
"C26020170927T071703017@import": {
        "ID"        :"C26020170927T071703017@import",
        "apogee"    :"4TBE902U",
        "acronym"   :"S09::EvoComm",
        "date_start":"2017-11-15T14:00",
        "date_end"  :"2017-11-15T18:00",
        "lecturer"  :"Fi&eacute;vet V",
        "location"  :"None::None@Room_000",
        "group"     :"All",
        "type"      :"Cours",
        "year"      :"2",
        "tracks"    :"0x60",
        "comment"   :"Imported from .ics - Wed Sep 27 2017 09:17:03 GMT+0200 (CEST)"},
"C20F20170927T071703018@import": {
        "ID"        :"C20F20170927T071703018@import",
        "apogee"    :"4TBI902U",
        "acronym"   :"S09::FILBI",
        "date_start":"2017-11-29T13:00",
        "date_end"  :"2017-11-29T15:00",
        "lecturer"  :"Th&eacute;bault P",
        "location"  :"Talence::A29-CREMI@Room_009",
        "group"     :"All",
        "type"      :"TD",
        "year"      :"2",
        "tracks"    :"0x0F",
        "comment"   :"Imported from .ics - Wed Sep 27 2017 09:17:03 GMT+0200 (CEST)"},
"C20F20170927T071703019@import": {
        "ID"        :"C20F20170927T071703019@import",
        "apogee"    :"4TBI902U",
        "acronym"   :"S09::FILBI",
        "date_start":"2017-12-08T09:00",
        "date_end"  :"2017-12-08T18:00",
        "lecturer"  :"Th&eacute;bault P",
        "location"  :"None::None@Room_000",
        "group"     :"All",
        "type"      :"Cours",
        "year"      :"2",
        "tracks"    :"0x0F",
        "comment"   :"Imported from .ics - Wed Sep 27 2017 09:17:03 GMT+0200 (CEST)"},
"C20F20170927T071703020@import": {
        "ID"        :"C20F20170927T071703020@import",
        "apogee"    :"4TBI902U",
        "acronym"   :"S09::FILBI",
        "date_start":"2017-12-08T09:00",
        "date_end"  :"2017-12-08T18:00",
        "lecturer"  :"Th&eacute;bault P",
        "location"  :"None::None@Room_000",
        "group"     :"All",
        "type"      :"Cours",
        "year"      :"2",
        "tracks"    :"0x0F",
        "comment"   :"Imported from .ics - Wed Sep 27 2017 09:17:03 GMT+0200 (CEST)"},
"C20F20170927T071703021@import": {
        "ID"        :"C20F20170927T071703021@import",
        "apogee"    :"4TBI902U",
        "acronym"   :"S09::FILBI",
        "date_start":"2017-10-26T14:00",
        "date_end"  :"2017-10-26T18:00",
        "lecturer"  :"de Daruvar A",
        "location"  :"None::None@Room_000",
        "group"     :"All",
        "type"      :"Cours",
        "year"      :"2",
        "tracks"    :"0x0F",
        "comment"   :"Imported from .ics - Wed Sep 27 2017 09:17:03 GMT+0200 (CEST)"},
"C20F20170927T071703022@import": {
        "ID"        :"C20F20170927T071703022@import",
        "apogee"    :"4TBI902U",
        "acronym"   :"S09::FILBI",
        "date_start":"2017-10-27T13:00",
        "date_end"  :"2017-10-27T18:00",
        "lecturer"  :"de Daruvar A",
        "location"  :"None::None@Room_000",
        "group"     :"All",
        "type"      :"Cours",
        "year"      :"2",
        "tracks"    :"0x0F",
        "comment"   :"Imported from .ics - Wed Sep 27 2017 09:17:03 GMT+0200 (CEST)"},
"C20F20170927T071703023@import": {
        "ID"        :"C20F20170927T071703023@import",
        "apogee"    :"4TBI902U",
        "acronym"   :"S09::FILBI",
        "date_start":"2017-10-03T08:00",
        "date_end"  :"2017-10-03T11:00",
        "lecturer"  :"Th&eacute;bault P",
        "location"  :"Talence::A29-CREMI@Room_207",
        "group"     :"All",
        "type"      :"Cours",
        "year"      :"2",
        "tracks"    :"0x0F",
        "comment"   :"Imported from .ics - Wed Sep 27 2017 09:17:03 GMT+0200 (CEST)"},
"C20F20170927T071703024@import": {
        "ID"        :"C20F20170927T071703024@import",
        "apogee"    :"4TBI902U",
        "acronym"   :"S09::FILBI",
        "date_start":"2017-10-10T08:00",
        "date_end"  :"2017-10-10T11:00",
        "lecturer"  :"Th&eacute;bault P",
        "location"  :"Talence::A29-CREMI@Room_207",
        "group"     :"All",
        "type"      :"Cours+TD",
        "year"      :"2",
        "tracks"    :"0x0F",
        "comment"   :"Imported from .ics - Wed Sep 27 2017 09:17:03 GMT+0200 (CEST)"},
"C20F20170927T071703025@import": {
        "ID"        :"C20F20170927T071703025@import",
        "apogee"    :"4TBI902U",
        "acronym"   :"S09::FILBI",
        "date_start":"2017-10-24T08:00",
        "date_end"  :"2017-10-24T11:00",
        "lecturer"  :"Th&eacute;bault P",
        "location"  :"Talence::A29-CREMI@Room_208",
        "group"     :"All",
        "type"      :"Cours+TD",
        "year"      :"2",
        "tracks"    :"0x0F",
        "comment"   :"Imported from .ics - Wed Sep 27 2017 09:17:03 GMT+0200 (CEST)"},
"C20F20170927T071703026@import": {
        "ID"        :"C20F20170927T071703026@import",
        "apogee"    :"4TBI902U",
        "acronym"   :"S09::FILBI",
        "date_start":"2017-12-05T09:00",
        "date_end"  :"2017-12-05T12:00",
        "lecturer"  :"Th&eacute;bault P",
        "location"  :"Talence::A30-LaBRI@ROOM_076",
        "group"     :"All",
        "type"      :"EXAMEN",
        "year"      :"2",
        "tracks"    :"0x0F",
        "comment"   :"Imported from .ics - Wed Sep 27 2017 09:17:03 GMT+0200 (CEST)"},
"C20F20170927T071703027@import": {
        "ID"        :"C20F20170927T071703027@import",
        "apogee"    :"4TBI902U",
        "acronym"   :"S09::FILBI",
        "date_start":"2017-12-15T08:00",
        "date_end"  :"2017-12-15T17:30",
        "lecturer"  :"Th&eacute;bault P",
        "location"  :"None::None@Room_000",
        "group"     :"All",
        "type"      :"Cours",
        "year"      :"2",
        "tracks"    :"0x0F",
        "comment"   :"Imported from .ics - Wed Sep 27 2017 09:17:03 GMT+0200 (CEST)"},
"C26120170927T071703028@import": {
        "ID"        :"C26120170927T071703028@import",
        "apogee"    :"4TBI903U",
        "acronym"   :"S09::GLog",
        "date_start":"2017-09-11T14:00",
        "date_end"  :"2017-09-11T17:00",
        "lecturer"  :"Grelard F",
        "location"  :"Talence::A29-CREMI@Room_000",
        "group"     :"All",
        "type"      :"Cours+TD",
        "year"      :"2",
        "tracks"    :"0x61",
        "comment"   :"Imported from .ics - Wed Sep 27 2017 09:17:03 GMT+0200 (CEST)"},
"C26120170927T071703029@import": {
        "ID"        :"C26120170927T071703029@import",
        "apogee"    :"4TBI903U",
        "acronym"   :"S09::GLog",
        "date_start":"2017-09-18T14:00",
        "date_end"  :"2017-09-18T17:00",
        "lecturer"  :"Beurton-Aimar M",
        "location"  :"Talence::A29-CREMI@Room_000",
        "group"     :"All",
        "type"      :"Cours+TD",
        "year"      :"2",
        "tracks"    :"0x61",
        "comment"   :"Imported from .ics - Wed Sep 27 2017 09:17:03 GMT+0200 (CEST)"},
"C26120170927T071703030@import": {
        "ID"        :"C26120170927T071703030@import",
        "apogee"    :"4TBI903U",
        "acronym"   :"S09::GLog",
        "date_start":"2017-09-25T14:00",
        "date_end"  :"2017-09-25T17:00",
        "lecturer"  :"Beurton-Aimar M",
        "location"  :"Talence::A29-CREMI@Room_000",
        "group"     :"All",
        "type"      :"Cours+TD",
        "year"      :"2",
        "tracks"    :"0x61",
        "comment"   :"Imported from .ics - Wed Sep 27 2017 09:17:03 GMT+0200 (CEST)"},
"C26120170927T071703031@import": {
        "ID"        :"C26120170927T071703031@import",
        "apogee"    :"4TBI903U",
        "acronym"   :"S09::GLog",
        "date_start":"2017-10-02T14:00",
        "date_end"  :"2017-10-02T17:00",
        "lecturer"  :"Beurton-Aimar M",
        "location"  :"Talence::A29-CREMI@Room_005",
        "group"     :"All",
        "type"      :"Cours+TD",
        "year"      :"2",
        "tracks"    :"0x61",
        "comment"   :"Imported from .ics - Wed Sep 27 2017 09:17:03 GMT+0200 (CEST)"},
"C26120170927T071703032@import": {
        "ID"        :"C26120170927T071703032@import",
        "apogee"    :"4TBI903U",
        "acronym"   :"S09::GLog",
        "date_start":"2017-10-09T14:00",
        "date_end"  :"2017-10-09T17:00",
        "lecturer"  :"Beurton-Aimar M",
        "location"  :"Talence::A29-CREMI@Room_005",
        "group"     :"All",
        "type"      :"Cours+TD",
        "year"      :"2",
        "tracks"    :"0x61",
        "comment"   :"Imported from .ics - Wed Sep 27 2017 09:17:03 GMT+0200 (CEST)"},
"C26120170927T071703033@import": {
        "ID"        :"C26120170927T071703033@import",
        "apogee"    :"4TBI903U",
        "acronym"   :"S09::GLog",
        "date_start":"2017-10-16T14:00",
        "date_end"  :"2017-10-16T17:00",
        "lecturer"  :"Beurton-Aimar M",
        "location"  :"Talence::A29-CREMI@Room_005",
        "group"     :"All",
        "type"      :"Cours+TD",
        "year"      :"2",
        "tracks"    :"0x61",
        "comment"   :"Imported from .ics - Wed Sep 27 2017 09:17:03 GMT+0200 (CEST)"},
"C26120170927T071703034@import": {
        "ID"        :"C26120170927T071703034@import",
        "apogee"    :"4TBI903U",
        "acronym"   :"S09::GLog",
        "date_start":"2017-10-23T14:00",
        "date_end"  :"2017-10-23T17:00",
        "lecturer"  :"Beurton-Aimar M",
        "location"  :"Talence::A29-CREMI@Room_005",
        "group"     :"All",
        "type"      :"Cours+TD",
        "year"      :"2",
        "tracks"    :"0x61",
        "comment"   :"Imported from .ics - Wed Sep 27 2017 09:17:03 GMT+0200 (CEST)"},
"C26120170927T071703035@import": {
        "ID"        :"C26120170927T071703035@import",
        "apogee"    :"4TBI903U",
        "acronym"   :"S09::GLog",
        "date_start":"2017-11-06T14:00",
        "date_end"  :"2017-11-06T17:00",
        "lecturer"  :"Beurton-Aimar M",
        "location"  :"Talence::A29-CREMI@Room_005",
        "group"     :"All",
        "type"      :"Cours+TD",
        "year"      :"2",
        "tracks"    :"0x61",
        "comment"   :"Imported from .ics - Wed Sep 27 2017 09:17:03 GMT+0200 (CEST)"},
"C26120170927T071703036@import": {
        "ID"        :"C26120170927T071703036@import",
        "apogee"    :"4TBI903U",
        "acronym"   :"S09::GLog",
        "date_start":"2017-11-13T14:00",
        "date_end"  :"2017-11-13T17:00",
        "lecturer"  :"Beurton-Aimar M",
        "location"  :"Talence::A29-CREMI@Room_005",
        "group"     :"All",
        "type"      :"Cours+TD",
        "year"      :"2",
        "tracks"    :"0x61",
        "comment"   :"Imported from .ics - Wed Sep 27 2017 09:17:03 GMT+0200 (CEST)"},
"C26120170927T071703037@import": {
        "ID"        :"C26120170927T071703037@import",
        "apogee"    :"4TBI903U",
        "acronym"   :"S09::GLog",
        "date_start":"2017-11-20T14:00",
        "date_end"  :"2017-11-20T17:00",
        "lecturer"  :"Beurton-Aimar M",
        "location"  :"Talence::A29-CREMI@Room_005",
        "group"     :"All",
        "type"      :"Cours+TD",
        "year"      :"2",
        "tracks"    :"0x61",
        "comment"   :"Imported from .ics - Wed Sep 27 2017 09:17:03 GMT+0200 (CEST)"},
"C26120170927T071703038@import": {
        "ID"        :"C26120170927T071703038@import",
        "apogee"    :"4TBI903U",
        "acronym"   :"S09::GLog",
        "date_start":"2017-11-27T14:00",
        "date_end"  :"2017-11-27T17:00",
        "lecturer"  :"Beurton-Aimar M",
        "location"  :"Talence::A29-CREMI@Room_005",
        "group"     :"All",
        "type"      :"Cours+TD",
        "year"      :"2",
        "tracks"    :"0x61",
        "comment"   :"Imported from .ics - Wed Sep 27 2017 09:17:03 GMT+0200 (CEST)"},
"C26120170927T071703039@import": {
        "ID"        :"C26120170927T071703039@import",
        "apogee"    :"4TBI903U",
        "acronym"   :"S09::GLog",
        "date_start":"2017-12-04T14:00",
        "date_end"  :"2017-12-04T17:00",
        "lecturer"  :"Beurton-Aimar M",
        "location"  :"Talence::A29-CREMI@Room_005",
        "group"     :"All",
        "type"      :"Cours+TD",
        "year"      :"2",
        "tracks"    :"0x61",
        "comment"   :"Imported from .ics - Wed Sep 27 2017 09:17:03 GMT+0200 (CEST)"},
"C26120170927T071703040@import": {
        "ID"        :"C26120170927T071703040@import",
        "apogee"    :"4TBI903U",
        "acronym"   :"S09::GLog",
        "date_start":"2017-12-11T14:00",
        "date_end"  :"2017-12-11T17:00",
        "lecturer"  :"Beurton-Aimar M",
        "location"  :"Talence::A29-CREMI@Room_005",
        "group"     :"All",
        "type"      :"Cours+TD",
        "year"      :"2",
        "tracks"    :"0x61",
        "comment"   :"Imported from .ics - Wed Sep 27 2017 09:17:03 GMT+0200 (CEST)"},
"C26020170927T071703041@import": {
        "ID"        :"C26020170927T071703041@import",
        "apogee"    :"4TDE902U",
        "acronym"   :"S09::IBS",
        "date_start":"2017-11-21T14:00",
        "date_end"  :"2017-11-21T18:00",
        "lecturer"  :"Beven L",
        "location"  :"None::None@Room_000",
        "group"     :"All",
        "type"      :"TP",
        "year"      :"2",
        "tracks"    :"0x60",
        "comment"   :"Imported from .ics - Wed Sep 27 2017 09:17:03 GMT+0200 (CEST)"},
"C26020170927T071703042@import": {
        "ID"        :"C26020170927T071703042@import",
        "apogee"    :"4TDE902U",
        "acronym"   :"S09::IBS",
        "date_start":"2017-11-22T08:00",
        "date_end"  :"2017-11-22T12:00",
        "lecturer"  :"Beven L",
        "location"  :"None::None@Room_000",
        "group"     :"All",
        "type"      :"TP",
        "year"      :"2",
        "tracks"    :"0x60",
        "comment"   :"Imported from .ics - Wed Sep 27 2017 09:17:03 GMT+0200 (CEST)"},
"C26020170927T071703043@import": {
        "ID"        :"C26020170927T071703043@import",
        "apogee"    :"4TDE902U",
        "acronym"   :"S09::IBS",
        "date_start":"2017-09-27T08:00",
        "date_end"  :"2017-09-27T10:00",
        "lecturer"  :"Beven L",
        "location"  :"None::None@Room_000",
        "group"     :"All",
        "type"      :"Cours",
        "year"      :"2",
        "tracks"    :"0x60",
        "comment"   :"Imported from .ics - Wed Sep 27 2017 09:17:03 GMT+0200 (CEST)"},
"C26020170927T071703044@import": {
        "ID"        :"C26020170927T071703044@import",
        "apogee"    :"4TDE902U",
        "acronym"   :"S09::IBS",
        "date_start":"2017-11-07T08:00",
        "date_end"  :"2017-11-07T12:00",
        "lecturer"  :"Beven L",
        "location"  :"None::None@Room_000",
        "group"     :"All",
        "type"      :"TD",
        "year"      :"2",
        "tracks"    :"0x60",
        "comment"   :"Imported from .ics - Wed Sep 27 2017 09:17:03 GMT+0200 (CEST)"},
"C26020170927T071703045@import": {
        "ID"        :"C26020170927T071703045@import",
        "apogee"    :"4TDE902U",
        "acronym"   :"S09::IBS",
        "date_start":"2017-11-14T14:00",
        "date_end"  :"2017-11-14T18:00",
        "lecturer"  :"Beven L",
        "location"  :"None::None@Room_000",
        "group"     :"All",
        "type"      :"TP",
        "year"      :"2",
        "tracks"    :"0x60",
        "comment"   :"Imported from .ics - Wed Sep 27 2017 09:17:03 GMT+0200 (CEST)"},
"C26020170927T071703046@import": {
        "ID"        :"C26020170927T071703046@import",
        "apogee"    :"4TDE902U",
        "acronym"   :"S09::IBS",
        "date_start":"2017-09-20T11:00",
        "date_end"  :"2017-09-20T12:00",
        "lecturer"  :"Beven L",
        "location"  :"None::None@Room_000",
        "group"     :"All",
        "type"      :"Cours",
        "year"      :"2",
        "tracks"    :"0x60",
        "comment"   :"Imported from .ics - Wed Sep 27 2017 09:17:03 GMT+0200 (CEST)"},
"C26020170927T071703047@import": {
        "ID"        :"C26020170927T071703047@import",
        "apogee"    :"4TDE902U",
        "acronym"   :"S09::IBS",
        "date_start":"2017-10-04T08:00",
        "date_end"  :"2017-10-04T12:00",
        "lecturer"  :"Beven L",
        "location"  :"None::None@Room_000",
        "group"     :"All",
        "type"      :"Cours",
        "year"      :"2",
        "tracks"    :"0x60",
        "comment"   :"Imported from .ics - Wed Sep 27 2017 09:17:03 GMT+0200 (CEST)"},
"C26020170927T071703048@import": {
        "ID"        :"C26020170927T071703048@import",
        "apogee"    :"4TDE902U",
        "acronym"   :"S09::IBS",
        "date_start":"2017-09-26T10:00",
        "date_end"  :"2017-09-26T12:00",
        "lecturer"  :"Beven L",
        "location"  :"None::None@Room_000",
        "group"     :"All",
        "type"      :"Cours",
        "year"      :"2",
        "tracks"    :"0x60",
        "comment"   :"Imported from .ics - Wed Sep 27 2017 09:17:03 GMT+0200 (CEST)"},
"C26020170927T071703049@import": {
        "ID"        :"C26020170927T071703049@import",
        "apogee"    :"4TDE902U",
        "acronym"   :"S09::IBS",
        "date_start":"2017-11-15T14:00",
        "date_end"  :"2017-11-15T18:00",
        "lecturer"  :"Beven L",
        "location"  :"None::None@Room_000",
        "group"     :"All",
        "type"      :"TP",
        "year"      :"2",
        "tracks"    :"0x60",
        "comment"   :"Imported from .ics - Wed Sep 27 2017 09:17:03 GMT+0200 (CEST)"},
"C26020170927T071703050@import": {
        "ID"        :"C26020170927T071703050@import",
        "apogee"    :"4TDE902U",
        "acronym"   :"S09::IBS",
        "date_start":"2017-09-13T10:00",
        "date_end"  :"2017-09-13T12:00",
        "lecturer"  :"Beven L",
        "location"  :"None::None@Room_000",
        "group"     :"All",
        "type"      :"Cours",
        "year"      :"2",
        "tracks"    :"0x60",
        "comment"   :"Imported from .ics - Wed Sep 27 2017 09:17:03 GMT+0200 (CEST)"},
"C26020170927T071703051@import": {
        "ID"        :"C26020170927T071703051@import",
        "apogee"    :"4TDE902U",
        "acronym"   :"S09::IBS",
        "date_start":"2017-09-15T10:00",
        "date_end"  :"2017-09-15T12:00",
        "lecturer"  :"Beven L",
        "location"  :"None::None@Room_000",
        "group"     :"All",
        "type"      :"Cours",
        "year"      :"2",
        "tracks"    :"0x60",
        "comment"   :"Imported from .ics - Wed Sep 27 2017 09:17:03 GMT+0200 (CEST)"},
"C26020170927T071703052@import": {
        "ID"        :"C26020170927T071703052@import",
        "apogee"    :"4TDE902U",
        "acronym"   :"S09::IBS",
        "date_start":"2017-11-10T08:00",
        "date_end"  :"2017-11-10T12:00",
        "lecturer"  :"DALENCON",
        "location"  :"None::None@Room_000",
        "group"     :"All",
        "type"      :"Cours",
        "year"      :"2",
        "tracks"    :"0x60",
        "comment"   :"Imported from .ics - Wed Sep 27 2017 09:17:03 GMT+0200 (CEST)"},
"C26020170927T071703053@import": {
        "ID"        :"C26020170927T071703053@import",
        "apogee"    :"4TDE902U",
        "acronym"   :"S09::IBS",
        "date_start":"2017-09-12T10:00",
        "date_end"  :"2017-09-12T12:00",
        "lecturer"  :"------",
        "location"  :"Carreire::ED@Room_27A",
        "group"     :"All",
        "type"      :"Cours",
        "year"      :"2",
        "tracks"    :"0x60",
        "comment"   :"Imported from .ics - Wed Sep 27 2017 09:17:03 GMT+0200 (CEST)"},
"C26020170927T071703054@import": {
        "ID"        :"C26020170927T071703054@import",
        "apogee"    :"4TDE902U",
        "acronym"   :"S09::IBS",
        "date_start":"2017-09-18T08:00",
        "date_end"  :"2017-09-18T12:00",
        "lecturer"  :"Beven L",
        "location"  :"None::None@Room_000",
        "group"     :"All",
        "type"      :"Cours",
        "year"      :"2",
        "tracks"    :"0x60",
        "comment"   :"Imported from .ics - Wed Sep 27 2017 09:17:03 GMT+0200 (CEST)"},
"C26020170927T071703055@import": {
        "ID"        :"C26020170927T071703055@import",
        "apogee"    :"4TDE902U",
        "acronym"   :"S09::IBS",
        "date_start":"2017-11-23T08:00",
        "date_end"  :"2017-11-23T12:00",
        "lecturer"  :"Beven L",
        "location"  :"None::None@Room_000",
        "group"     :"All",
        "type"      :"TP",
        "year"      :"2",
        "tracks"    :"0x60",
        "comment"   :"Imported from .ics - Wed Sep 27 2017 09:17:03 GMT+0200 (CEST)"},
"C26020170927T071703056@import": {
        "ID"        :"C26020170927T071703056@import",
        "apogee"    :"4TDE902U",
        "acronym"   :"S09::IBS",
        "date_start":"2017-09-22T10:00",
        "date_end"  :"2017-09-22T12:00",
        "lecturer"  :"Beven L",
        "location"  :"None::None@Room_000",
        "group"     :"All",
        "type"      :"Cours",
        "year"      :"2",
        "tracks"    :"0x60",
        "comment"   :"Imported from .ics - Wed Sep 27 2017 09:17:03 GMT+0200 (CEST)"},
"C26020170927T071703057@import": {
        "ID"        :"C26020170927T071703057@import",
        "apogee"    :"4TDE902U",
        "acronym"   :"S09::IBS",
        "date_start":"2017-10-10T08:00",
        "date_end"  :"2017-10-10T12:00",
        "lecturer"  :"Beven L",
        "location"  :"None::None@Room_000",
        "group"     :"All",
        "type"      :"Cours",
        "year"      :"2",
        "tracks"    :"0x60",
        "comment"   :"Imported from .ics - Wed Sep 27 2017 09:17:03 GMT+0200 (CEST)"},
"C26020170927T071703058@import": {
        "ID"        :"C26020170927T071703058@import",
        "apogee"    :"4TDE902U",
        "acronym"   :"S09::IBS",
        "date_start":"2017-10-24T10:00",
        "date_end"  :"2017-10-24T12:00",
        "lecturer"  :"Beven L",
        "location"  :"None::None@Room_000",
        "group"     :"All",
        "type"      :"TD",
        "year"      :"2",
        "tracks"    :"0x60",
        "comment"   :"Imported from .ics - Wed Sep 27 2017 09:17:03 GMT+0200 (CEST)"},
"C26020170927T071703059@import": {
        "ID"        :"C26020170927T071703059@import",
        "apogee"    :"4TDE902U",
        "acronym"   :"S09::IBS",
        "date_start":"2017-11-22T14:00",
        "date_end"  :"2017-11-22T18:00",
        "lecturer"  :"Beven L",
        "location"  :"None::None@Room_000",
        "group"     :"All",
        "type"      :"TP",
        "year"      :"2",
        "tracks"    :"0x60",
        "comment"   :"Imported from .ics - Wed Sep 27 2017 09:17:03 GMT+0200 (CEST)"},
"C26020170927T071703060@import": {
        "ID"        :"C26020170927T071703060@import",
        "apogee"    :"4TDE902U",
        "acronym"   :"S09::IBS",
        "date_start":"2017-09-25T10:00",
        "date_end"  :"2017-09-25T12:00",
        "lecturer"  :"Beven L",
        "location"  :"None::None@Room_000",
        "group"     :"All",
        "type"      :"Cours",
        "year"      :"2",
        "tracks"    :"0x60",
        "comment"   :"Imported from .ics - Wed Sep 27 2017 09:17:03 GMT+0200 (CEST)"},
"C26020170927T071703061@import": {
        "ID"        :"C26020170927T071703061@import",
        "apogee"    :"4TDE902U",
        "acronym"   :"S09::IBS",
        "date_start":"2017-10-02T09:00",
        "date_end"  :"2017-10-02T12:00",
        "lecturer"  :"Beven L",
        "location"  :"None::None@Room_000",
        "group"     :"All",
        "type"      :"Cours",
        "year"      :"2",
        "tracks"    :"0x60",
        "comment"   :"Imported from .ics - Wed Sep 27 2017 09:17:03 GMT+0200 (CEST)"},
"C27020170927T071703062@import": {
        "ID"        :"C27020170927T071703062@import",
        "apogee"    :"4TBI906U",
        "acronym"   :"S09::MOCELL",
        "date_start":"2017-09-13T08:00",
        "date_end"  :"2017-09-13T11:00",
        "lecturer"  :"Th&eacute;bault P",
        "location"  :"None::None@Room_000",
        "group"     :"All",
        "type"      :"Cours+TD",
        "year"      :"2",
        "tracks"    :"0x70",
        "comment"   :"Imported from .ics - Wed Sep 27 2017 09:17:03 GMT+0200 (CEST)"},
"C27020170927T071703063@import": {
        "ID"        :"C27020170927T071703063@import",
        "apogee"    :"4TBI906U",
        "acronym"   :"S09::MOCELL",
        "date_start":"2017-09-20T08:00",
        "date_end"  :"2017-09-20T11:00",
        "lecturer"  :"de Daruvar A",
        "location"  :"Talence::A29-CREMI@Room_203",
        "group"     :"All",
        "type"      :"Cours+TD",
        "year"      :"2",
        "tracks"    :"0x70",
        "comment"   :"Imported from .ics - Wed Sep 27 2017 09:17:03 GMT+0200 (CEST)"},
"C27020170927T071703064@import": {
        "ID"        :"C27020170927T071703064@import",
        "apogee"    :"4TBI906U",
        "acronym"   :"S09::MOCELL",
        "date_start":"2017-09-27T08:00",
        "date_end"  :"2017-09-27T11:00",
        "lecturer"  :"Th&eacute;bault P",
        "location"  :"Talence::A29-CREMI@Room_203",
        "group"     :"All",
        "type"      :"Cours+TD",
        "year"      :"2",
        "tracks"    :"0x70",
        "comment"   :"Imported from .ics - Wed Sep 27 2017 09:17:03 GMT+0200 (CEST)"},
"C27020170927T071703065@import": {
        "ID"        :"C27020170927T071703065@import",
        "apogee"    :"4TBI906U",
        "acronym"   :"S09::MOCELL",
        "date_start":"2017-10-04T08:00",
        "date_end"  :"2017-10-04T11:00",
        "lecturer"  :"Th&eacute;bault P",
        "location"  :"Talence::A29-CREMI@Room_203",
        "group"     :"All",
        "type"      :"Cours+TD",
        "year"      :"2",
        "tracks"    :"0x70",
        "comment"   :"Imported from .ics - Wed Sep 27 2017 09:17:03 GMT+0200 (CEST)"},
"C27020170927T071703066@import": {
        "ID"        :"C27020170927T071703066@import",
        "apogee"    :"4TBI906U",
        "acronym"   :"S09::MOCELL",
        "date_start":"2017-10-11T08:00",
        "date_end"  :"2017-10-11T11:00",
        "lecturer"  :"de Daruvar A",
        "location"  :"Talence::A29-CREMI@Room_203",
        "group"     :"All",
        "type"      :"Cours+TD",
        "year"      :"2",
        "tracks"    :"0x70",
        "comment"   :"Imported from .ics - Wed Sep 27 2017 09:17:03 GMT+0200 (CEST)"},
"C27020170927T071703067@import": {
        "ID"        :"C27020170927T071703067@import",
        "apogee"    :"4TBI906U",
        "acronym"   :"S09::MOCELL",
        "date_start":"2017-10-18T08:00",
        "date_end"  :"2017-10-18T11:00",
        "lecturer"  :"de Daruvar A",
        "location"  :"Talence::A29-CREMI@Room_203",
        "group"     :"All",
        "type"      :"Cours+TD",
        "year"      :"2",
        "tracks"    :"0x70",
        "comment"   :"Imported from .ics - Wed Sep 27 2017 09:17:03 GMT+0200 (CEST)"},
"C27020170927T071703068@import": {
        "ID"        :"C27020170927T071703068@import",
        "apogee"    :"4TBI906U",
        "acronym"   :"S09::MOCELL",
        "date_start":"2017-10-25T08:00",
        "date_end"  :"2017-10-25T11:00",
        "lecturer"  :"de Daruvar A",
        "location"  :"Talence::A29-CREMI@Room_203",
        "group"     :"All",
        "type"      :"Cours+TD",
        "year"      :"2",
        "tracks"    :"0x70",
        "comment"   :"Imported from .ics - Wed Sep 27 2017 09:17:03 GMT+0200 (CEST)"},
"C27020170927T071703069@import": {
        "ID"        :"C27020170927T071703069@import",
        "apogee"    :"4TBI906U",
        "acronym"   :"S09::MOCELL",
        "date_start":"2017-11-08T09:30",
        "date_end"  :"2017-11-08T11:30",
        "lecturer"  :"Beauvoit B",
        "location"  :"Talence::A29-CREMI@Room_205",
        "group"     :"All",
        "type"      :"Cours+TD",
        "year"      :"2",
        "tracks"    :"0x70",
        "comment"   :"Imported from .ics - Wed Sep 27 2017 09:17:03 GMT+0200 (CEST)"},
"C27020170927T071703070@import": {
        "ID"        :"C27020170927T071703070@import",
        "apogee"    :"4TBI906U",
        "acronym"   :"S09::MOCELL",
        "date_start":"2017-11-08T13:00",
        "date_end"  :"2017-11-08T15:00",
        "lecturer"  :"Dieuaide M",
        "location"  :"Talence::A29-CREMI@Room_005",
        "group"     :"All",
        "type"      :"Cours+TD",
        "year"      :"2",
        "tracks"    :"0x70",
        "comment"   :"Imported from .ics - Wed Sep 27 2017 09:17:03 GMT+0200 (CEST)"},
"C27020170927T071703071@import": {
        "ID"        :"C27020170927T071703071@import",
        "apogee"    :"4TBI906U",
        "acronym"   :"S09::MOCELL",
        "date_start":"2017-11-29T09:30",
        "date_end"  :"2017-11-29T11:30",
        "lecturer"  :"COLOMBIER",
        "location"  :"Talence::A29-CREMI@Room_205",
        "group"     :"All",
        "type"      :"Cours+TD",
        "year"      :"2",
        "tracks"    :"0x70",
        "comment"   :"Imported from .ics - Wed Sep 27 2017 09:17:03 GMT+0200 (CEST)"},
"C27020170927T071703072@import": {
        "ID"        :"C27020170927T071703072@import",
        "apogee"    :"4TBI906U",
        "acronym"   :"S09::MOCELL",
        "date_start":"2017-11-22T13:00",
        "date_end"  :"2017-11-22T15:00",
        "lecturer"  :"Dieuaide M",
        "location"  :"Talence::A29-CREMI@Room_009",
        "group"     :"All",
        "type"      :"Cours+TD",
        "year"      :"2",
        "tracks"    :"0x70",
        "comment"   :"Imported from .ics - Wed Sep 27 2017 09:17:03 GMT+0200 (CEST)"},
"C27020170927T071703073@import": {
        "ID"        :"C27020170927T071703073@import",
        "apogee"    :"4TBI906U",
        "acronym"   :"S09::MOCELL",
        "date_start":"2017-11-22T09:30",
        "date_end"  :"2017-11-22T11:30",
        "lecturer"  :"COLOMBIER",
        "location"  :"Talence::A29-CREMI@Room_205",
        "group"     :"All",
        "type"      :"Cours+TD",
        "year"      :"2",
        "tracks"    :"0x70",
        "comment"   :"Imported from .ics - Wed Sep 27 2017 09:17:03 GMT+0200 (CEST)"},
"C27020170927T071703074@import": {
        "ID"        :"C27020170927T071703074@import",
        "apogee"    :"4TBI906U",
        "acronym"   :"S09::MOCELL",
        "date_start":"2017-11-15T09:30",
        "date_end"  :"2017-11-15T11:30",
        "lecturer"  :"COLOMBIER",
        "location"  :"Talence::A29-CREMI@Room_205",
        "group"     :"All",
        "type"      :"Cours+TD",
        "year"      :"2",
        "tracks"    :"0x70",
        "comment"   :"Imported from .ics - Wed Sep 27 2017 09:17:03 GMT+0200 (CEST)"},
"C27020170927T071703075@import": {
        "ID"        :"C27020170927T071703075@import",
        "apogee"    :"4TBI906U",
        "acronym"   :"S09::MOCELL",
        "date_start":"2017-11-15T13:00",
        "date_end"  :"2017-11-15T15:00",
        "lecturer"  :"Beauvoit B",
        "location"  :"Talence::A29-CREMI@Room_009",
        "group"     :"All",
        "type"      :"Cours+TD",
        "year"      :"2",
        "tracks"    :"0x70",
        "comment"   :"Imported from .ics - Wed Sep 27 2017 09:17:03 GMT+0200 (CEST)"},
"C27020170927T071703076@import": {
        "ID"        :"C27020170927T071703076@import",
        "apogee"    :"4TBI906U",
        "acronym"   :"S09::MOCELL",
        "date_start":"2017-12-06T09:30",
        "date_end"  :"2017-12-06T11:30",
        "lecturer"  :"Beauvoit B",
        "location"  :"Talence::A29-CREMI@Room_205",
        "group"     :"All",
        "type"      :"Cours+TD",
        "year"      :"2",
        "tracks"    :"0x70",
        "comment"   :"Imported from .ics - Wed Sep 27 2017 09:17:03 GMT+0200 (CEST)"},
"C27020170927T071703077@import": {
        "ID"        :"C27020170927T071703077@import",
        "apogee"    :"4TBI906U",
        "acronym"   :"S09::MOCELL",
        "date_start":"2017-12-06T13:00",
        "date_end"  :"2017-12-06T15:00",
        "lecturer"  :"Dieuaide M",
        "location"  :"Talence::A29-CREMI@Room_009",
        "group"     :"All",
        "type"      :"Cours+TD",
        "year"      :"2",
        "tracks"    :"0x70",
        "comment"   :"Imported from .ics - Wed Sep 27 2017 09:17:03 GMT+0200 (CEST)"},
"C27020170927T071703078@import": {
        "ID"        :"C27020170927T071703078@import",
        "apogee"    :"4TBI906U",
        "acronym"   :"S09::MOCELL",
        "date_start":"2017-12-13T09:30",
        "date_end"  :"2017-12-13T11:30",
        "lecturer"  :"COLOMBIER",
        "location"  :"Talence::A29-CREMI@Room_205",
        "group"     :"All",
        "type"      :"Cours+TD",
        "year"      :"2",
        "tracks"    :"0x70",
        "comment"   :"Imported from .ics - Wed Sep 27 2017 09:17:03 GMT+0200 (CEST)"},
"C27020170927T071703079@import": {
        "ID"        :"C27020170927T071703079@import",
        "apogee"    :"4TBI906U",
        "acronym"   :"S09::MOCELL",
        "date_start":"2017-12-13T13:00",
        "date_end"  :"2017-12-13T15:00",
        "lecturer"  :"Beauvoit B",
        "location"  :"Talence::A29-CREMI@Room_009",
        "group"     :"All",
        "type"      :"Cours+TD",
        "year"      :"2",
        "tracks"    :"0x70",
        "comment"   :"Imported from .ics - Wed Sep 27 2017 09:17:03 GMT+0200 (CEST)"},
"C26020170927T071703080@import": {
        "ID"        :"C26020170927T071703080@import",
        "apogee"    :"4TBA904U",
        "acronym"   :"S09::PDR",
        "date_start":"2017-09-13T10:00",
        "date_end"  :"2017-09-13T14:00",
        "lecturer"  :"------",
        "location"  :"INRA::IBVM@Room_IBVM",
        "group"     :"All",
        "type"      :"Cours+TD",
        "year"      :"2",
        "tracks"    :"0x60",
        "comment"   :"Imported from .ics - Wed Sep 27 2017 09:17:03 GMT+0200 (CEST)"},
"C26020170927T071703081@import": {
        "ID"        :"C26020170927T071703081@import",
        "apogee"    :"4TBA904U",
        "acronym"   :"S09::PDR",
        "date_start":"2017-09-15T16:00",
        "date_end"  :"2017-09-15T18:00",
        "lecturer"  :"------",
        "location"  :"INRA::IBVM@Room_IBVM",
        "group"     :"All",
        "type"      :"Cours+TD",
        "year"      :"2",
        "tracks"    :"0x60",
        "comment"   :"Imported from .ics - Wed Sep 27 2017 09:17:03 GMT+0200 (CEST)"},
"C26020170927T071703082@import": {
        "ID"        :"C26020170927T071703082@import",
        "apogee"    :"4TBA904U",
        "acronym"   :"S09::PDR",
        "date_start":"2017-09-20T16:00",
        "date_end"  :"2017-09-20T18:00",
        "lecturer"  :"------",
        "location"  :"INRA::IBVM@Room_IBVM",
        "group"     :"All",
        "type"      :"Cours+TD",
        "year"      :"2",
        "tracks"    :"0x60",
        "comment"   :"Imported from .ics - Wed Sep 27 2017 09:17:03 GMT+0200 (CEST)"},
"C26020170927T071703083@import": {
        "ID"        :"C26020170927T071703083@import",
        "apogee"    :"4TBA904U",
        "acronym"   :"S09::PDR",
        "date_start":"2017-09-27T08:00",
        "date_end"  :"2017-09-27T12:00",
        "lecturer"  :"------",
        "location"  :"INRA::IBVM@Room_002",
        "group"     :"All",
        "type"      :"Cours+TD",
        "year"      :"2",
        "tracks"    :"0x60",
        "comment"   :"Imported from .ics - Wed Sep 27 2017 09:17:03 GMT+0200 (CEST)"},
"C26020170927T071703084@import": {
        "ID"        :"C26020170927T071703084@import",
        "apogee"    :"4TBA904U",
        "acronym"   :"S09::PDR",
        "date_start":"2017-10-04T08:00",
        "date_end"  :"2017-10-04T12:00",
        "lecturer"  :"------",
        "location"  :"INRA::IBVM@Room_IBVM",
        "group"     :"All",
        "type"      :"Cours+TD",
        "year"      :"2",
        "tracks"    :"0x60",
        "comment"   :"Imported from .ics - Wed Sep 27 2017 09:17:03 GMT+0200 (CEST)"},
"C26020170927T071703085@import": {
        "ID"        :"C26020170927T071703085@import",
        "apogee"    :"4TBA904U",
        "acronym"   :"S09::PDR",
        "date_start":"2017-10-11T08:00",
        "date_end"  :"2017-10-11T12:00",
        "lecturer"  :"------",
        "location"  :"INRA::IBVM@Room_IBVM",
        "group"     :"All",
        "type"      :"Cours+TD",
        "year"      :"2",
        "tracks"    :"0x60",
        "comment"   :"Imported from .ics - Wed Sep 27 2017 09:17:03 GMT+0200 (CEST)"},
"C26020170927T071703086@import": {
        "ID"        :"C26020170927T071703086@import",
        "apogee"    :"4TBA904U",
        "acronym"   :"S09::PDR",
        "date_start":"2017-10-18T14:00",
        "date_end"  :"2017-10-18T18:00",
        "lecturer"  :"------",
        "location"  :"INRA::IBVM@Room_IBVM",
        "group"     :"All",
        "type"      :"Cours+TD",
        "year"      :"2",
        "tracks"    :"0x60",
        "comment"   :"Imported from .ics - Wed Sep 27 2017 09:17:03 GMT+0200 (CEST)"},
"C26020170927T071703087@import": {
        "ID"        :"C26020170927T071703087@import",
        "apogee"    :"4TBA904U",
        "acronym"   :"S09::PDR",
        "date_start":"2017-10-20T14:00",
        "date_end"  :"2017-10-20T18:00",
        "lecturer"  :"------",
        "location"  :"INRA::IBVM@Room_IBVM",
        "group"     :"All",
        "type"      :"Cours+TD",
        "year"      :"2",
        "tracks"    :"0x60",
        "comment"   :"Imported from .ics - Wed Sep 27 2017 09:17:03 GMT+0200 (CEST)"},
"C26020170927T071703088@import": {
        "ID"        :"C26020170927T071703088@import",
        "apogee"    :"4TBA904U",
        "acronym"   :"S09::PDR",
        "date_start":"2017-10-23T08:00",
        "date_end"  :"2017-10-23T12:00",
        "lecturer"  :"------",
        "location"  :"INRA::IBVM@Room_viro",
        "group"     :"All",
        "type"      :"Cours+TD",
        "year"      :"2",
        "tracks"    :"0x60",
        "comment"   :"Imported from .ics - Wed Sep 27 2017 09:17:03 GMT+0200 (CEST)"},
"C26020170927T071703089@import": {
        "ID"        :"C26020170927T071703089@import",
        "apogee"    :"4TBA904U",
        "acronym"   :"S09::PDR",
        "date_start":"2017-10-25T14:00",
        "date_end"  :"2017-10-25T18:00",
        "lecturer"  :"------",
        "location"  :"INRA::IBVM@Room_IBVM",
        "group"     :"All",
        "type"      :"Cours+TD",
        "year"      :"2",
        "tracks"    :"0x60",
        "comment"   :"Imported from .ics - Wed Sep 27 2017 09:17:03 GMT+0200 (CEST)"},
"C26020170927T071703090@import": {
        "ID"        :"C26020170927T071703090@import",
        "apogee"    :"4TBA904U",
        "acronym"   :"S09::PDR",
        "date_start":"2017-11-28T14:00",
        "date_end"  :"2017-11-28T18:00",
        "lecturer"  :"------",
        "location"  :"INRA::IBVM@Room_IBVM",
        "group"     :"All",
        "type"      :"Cours+TD",
        "year"      :"2",
        "tracks"    :"0x60",
        "comment"   :"Imported from .ics - Wed Sep 27 2017 09:17:03 GMT+0200 (CEST)"},
"C21020170927T071703091@import": {
        "ID"        :"C21020170927T071703091@import",
        "apogee"    :"4TBC901U",
        "acronym"   :"S09::POO++",
        "date_start":"2017-11-28T14:00",
        "date_end"  :"2017-11-28T16:00",
        "lecturer"  :"Cl&eacute;ment L",
        "location"  :"None::None@Room_000",
        "group"     :"All",
        "type"      :"Cours",
        "year"      :"2",
        "tracks"    :"0x10",
        "comment"   :"Imported from .ics - Wed Sep 27 2017 09:17:03 GMT+0200 (CEST)"},
"C21020170927T071703092@import": {
        "ID"        :"C21020170927T071703092@import",
        "apogee"    :"4TBC901U",
        "acronym"   :"S09::POO++",
        "date_start":"2017-09-26T14:00",
        "date_end"  :"2017-09-26T16:00",
        "lecturer"  :"Cl&eacute;ment L",
        "location"  :"None::None@Room_000",
        "group"     :"All",
        "type"      :"Cours",
        "year"      :"2",
        "tracks"    :"0x10",
        "comment"   :"Imported from .ics - Wed Sep 27 2017 09:17:03 GMT+0200 (CEST)"},
"C21020170927T071703093@import": {
        "ID"        :"C21020170927T071703093@import",
        "apogee"    :"4TBC901U",
        "acronym"   :"S09::POO++",
        "date_start":"2017-10-04T08:00",
        "date_end"  :"2017-10-04T10:00",
        "lecturer"  :"Cl&eacute;ment L",
        "location"  :"None::None@Room_000",
        "group"     :"All",
        "type"      :"TD",
        "year"      :"2",
        "tracks"    :"0x10",
        "comment"   :"Imported from .ics - Wed Sep 27 2017 09:17:03 GMT+0200 (CEST)"},
"C21020170927T071703094@import": {
        "ID"        :"C21020170927T071703094@import",
        "apogee"    :"4TBC901U",
        "acronym"   :"S09::POO++",
        "date_start":"2017-10-11T08:00",
        "date_end"  :"2017-10-11T10:00",
        "lecturer"  :"Cl&eacute;ment L",
        "location"  :"None::None@Room_000",
        "group"     :"All",
        "type"      :"TD",
        "year"      :"2",
        "tracks"    :"0x10",
        "comment"   :"Imported from .ics - Wed Sep 27 2017 09:17:03 GMT+0200 (CEST)"},
"C21020170927T071703095@import": {
        "ID"        :"C21020170927T071703095@import",
        "apogee"    :"4TBC901U",
        "acronym"   :"S09::POO++",
        "date_start":"2017-11-21T16:00",
        "date_end"  :"2017-11-21T18:00",
        "lecturer"  :"Cl&eacute;ment L",
        "location"  :"None::None@Room_000",
        "group"     :"All",
        "type"      :"TD",
        "year"      :"2",
        "tracks"    :"0x10",
        "comment"   :"Imported from .ics - Wed Sep 27 2017 09:17:03 GMT+0200 (CEST)"},
"C21020170927T071703096@import": {
        "ID"        :"C21020170927T071703096@import",
        "apogee"    :"4TBC901U",
        "acronym"   :"S09::POO++",
        "date_start":"2017-10-17T16:00",
        "date_end"  :"2017-10-17T18:00",
        "lecturer"  :"Cl&eacute;ment L",
        "location"  :"None::None@Room_000",
        "group"     :"All",
        "type"      :"TD",
        "year"      :"2",
        "tracks"    :"0x10",
        "comment"   :"Imported from .ics - Wed Sep 27 2017 09:17:03 GMT+0200 (CEST)"},
"C21020170927T071703097@import": {
        "ID"        :"C21020170927T071703097@import",
        "apogee"    :"4TBC901U",
        "acronym"   :"S09::POO++",
        "date_start":"2017-11-15T08:00",
        "date_end"  :"2017-11-15T10:00",
        "lecturer"  :"Cl&eacute;ment L",
        "location"  :"None::None@Room_000",
        "group"     :"All",
        "type"      :"TD",
        "year"      :"2",
        "tracks"    :"0x10",
        "comment"   :"Imported from .ics - Wed Sep 27 2017 09:17:03 GMT+0200 (CEST)"},
"C21020170927T071703098@import": {
        "ID"        :"C21020170927T071703098@import",
        "apogee"    :"4TBC901U",
        "acronym"   :"S09::POO++",
        "date_start":"2017-10-10T14:00",
        "date_end"  :"2017-10-10T16:00",
        "lecturer"  :"Cl&eacute;ment L",
        "location"  :"None::None@Room_000",
        "group"     :"All",
        "type"      :"Cours",
        "year"      :"2",
        "tracks"    :"0x10",
        "comment"   :"Imported from .ics - Wed Sep 27 2017 09:17:03 GMT+0200 (CEST)"},
"C21020170927T071703099@import": {
        "ID"        :"C21020170927T071703099@import",
        "apogee"    :"4TBC901U",
        "acronym"   :"S09::POO++",
        "date_start":"2017-10-17T14:00",
        "date_end"  :"2017-10-17T16:00",
        "lecturer"  :"Cl&eacute;ment L",
        "location"  :"None::None@Room_000",
        "group"     :"All",
        "type"      :"Cours",
        "year"      :"2",
        "tracks"    :"0x10",
        "comment"   :"Imported from .ics - Wed Sep 27 2017 09:17:03 GMT+0200 (CEST)"},
"C21020170927T071703100@import": {
        "ID"        :"C21020170927T071703100@import",
        "apogee"    :"4TBC901U",
        "acronym"   :"S09::POO++",
        "date_start":"2017-09-12T16:00",
        "date_end"  :"2017-09-12T18:00",
        "lecturer"  :"Cl&eacute;ment L",
        "location"  :"None::None@Room_000",
        "group"     :"All",
        "type"      :"TD",
        "year"      :"2",
        "tracks"    :"0x10",
        "comment"   :"Imported from .ics - Wed Sep 27 2017 09:17:03 GMT+0200 (CEST)"},
"C21020170927T071703101@import": {
        "ID"        :"C21020170927T071703101@import",
        "apogee"    :"4TBC901U",
        "acronym"   :"S09::POO++",
        "date_start":"2017-10-25T08:00",
        "date_end"  :"2017-10-25T10:00",
        "lecturer"  :"Cl&eacute;ment L",
        "location"  :"None::None@Room_000",
        "group"     :"All",
        "type"      :"TD",
        "year"      :"2",
        "tracks"    :"0x10",
        "comment"   :"Imported from .ics - Wed Sep 27 2017 09:17:03 GMT+0200 (CEST)"},
"C21020170927T071703102@import": {
        "ID"        :"C21020170927T071703102@import",
        "apogee"    :"4TBC901U",
        "acronym"   :"S09::POO++",
        "date_start":"2017-11-28T16:00",
        "date_end"  :"2017-11-28T18:00",
        "lecturer"  :"Cl&eacute;ment L",
        "location"  :"None::None@Room_000",
        "group"     :"All",
        "type"      :"TD",
        "year"      :"2",
        "tracks"    :"0x10",
        "comment"   :"Imported from .ics - Wed Sep 27 2017 09:17:03 GMT+0200 (CEST)"},
"C21020170927T071703103@import": {
        "ID"        :"C21020170927T071703103@import",
        "apogee"    :"4TBC901U",
        "acronym"   :"S09::POO++",
        "date_start":"2017-11-22T08:00",
        "date_end"  :"2017-11-22T10:00",
        "lecturer"  :"Cl&eacute;ment L",
        "location"  :"None::None@Room_000",
        "group"     :"All",
        "type"      :"TD",
        "year"      :"2",
        "tracks"    :"0x10",
        "comment"   :"Imported from .ics - Wed Sep 27 2017 09:17:03 GMT+0200 (CEST)"},
"C21020170927T071703104@import": {
        "ID"        :"C21020170927T071703104@import",
        "apogee"    :"4TBC901U",
        "acronym"   :"S09::POO++",
        "date_start":"2017-09-27T08:00",
        "date_end"  :"2017-09-27T10:00",
        "lecturer"  :"Cl&eacute;ment L",
        "location"  :"None::None@Room_000",
        "group"     :"All",
        "type"      :"TD",
        "year"      :"2",
        "tracks"    :"0x10",
        "comment"   :"Imported from .ics - Wed Sep 27 2017 09:17:03 GMT+0200 (CEST)"},
"C21020170927T071703105@import": {
        "ID"        :"C21020170927T071703105@import",
        "apogee"    :"4TBC901U",
        "acronym"   :"S09::POO++",
        "date_start":"2017-12-06T08:00",
        "date_end"  :"2017-12-06T10:00",
        "lecturer"  :"Cl&eacute;ment L",
        "location"  :"None::None@Room_000",
        "group"     :"All",
        "type"      :"TD",
        "year"      :"2",
        "tracks"    :"0x10",
        "comment"   :"Imported from .ics - Wed Sep 27 2017 09:17:03 GMT+0200 (CEST)"},
"C21020170927T071703106@import": {
        "ID"        :"C21020170927T071703106@import",
        "apogee"    :"4TBC901U",
        "acronym"   :"S09::POO++",
        "date_start":"2017-09-05T14:00",
        "date_end"  :"2017-09-05T16:00",
        "lecturer"  :"Cl&eacute;ment L",
        "location"  :"Talence::A9@Amphi_002",
        "group"     :"All",
        "type"      :"Cours",
        "year"      :"2",
        "tracks"    :"0x10",
        "comment"   :"Imported from .ics - Wed Sep 27 2017 09:17:03 GMT+0200 (CEST)"},
"C21020170927T071703107@import": {
        "ID"        :"C21020170927T071703107@import",
        "apogee"    :"4TBC901U",
        "acronym"   :"S09::POO++",
        "date_start":"2017-10-24T14:00",
        "date_end"  :"2017-10-24T16:00",
        "lecturer"  :"Cl&eacute;ment L",
        "location"  :"None::None@Room_000",
        "group"     :"All",
        "type"      :"Cours",
        "year"      :"2",
        "tracks"    :"0x10",
        "comment"   :"Imported from .ics - Wed Sep 27 2017 09:17:03 GMT+0200 (CEST)"},
"C21020170927T071703108@import": {
        "ID"        :"C21020170927T071703108@import",
        "apogee"    :"4TBC901U",
        "acronym"   :"S09::POO++",
        "date_start":"2017-09-19T14:00",
        "date_end"  :"2017-09-19T16:00",
        "lecturer"  :"Cl&eacute;ment L",
        "location"  :"None::None@Room_000",
        "group"     :"All",
        "type"      :"Cours",
        "year"      :"2",
        "tracks"    :"0x10",
        "comment"   :"Imported from .ics - Wed Sep 27 2017 09:17:03 GMT+0200 (CEST)"},
"C21020170927T071703109@import": {
        "ID"        :"C21020170927T071703109@import",
        "apogee"    :"4TBC901U",
        "acronym"   :"S09::POO++",
        "date_start":"2017-10-24T16:00",
        "date_end"  :"2017-10-24T18:00",
        "lecturer"  :"Cl&eacute;ment L",
        "location"  :"None::None@Room_000",
        "group"     :"All",
        "type"      :"TD",
        "year"      :"2",
        "tracks"    :"0x10",
        "comment"   :"Imported from .ics - Wed Sep 27 2017 09:17:03 GMT+0200 (CEST)"},
"C21020170927T071703110@import": {
        "ID"        :"C21020170927T071703110@import",
        "apogee"    :"4TBC901U",
        "acronym"   :"S09::POO++",
        "date_start":"2017-11-08T08:00",
        "date_end"  :"2017-11-08T10:00",
        "lecturer"  :"Cl&eacute;ment L",
        "location"  :"None::None@Room_000",
        "group"     :"All",
        "type"      :"TD",
        "year"      :"2",
        "tracks"    :"0x10",
        "comment"   :"Imported from .ics - Wed Sep 27 2017 09:17:03 GMT+0200 (CEST)"},
"C21020170927T071703111@import": {
        "ID"        :"C21020170927T071703111@import",
        "apogee"    :"4TBC901U",
        "acronym"   :"S09::POO++",
        "date_start":"2017-10-03T14:00",
        "date_end"  :"2017-10-03T16:00",
        "lecturer"  :"Cl&eacute;ment L",
        "location"  :"None::None@Room_000",
        "group"     :"All",
        "type"      :"Cours",
        "year"      :"2",
        "tracks"    :"0x10",
        "comment"   :"Imported from .ics - Wed Sep 27 2017 09:17:03 GMT+0200 (CEST)"},
"C21020170927T071703112@import": {
        "ID"        :"C21020170927T071703112@import",
        "apogee"    :"4TBC901U",
        "acronym"   :"S09::POO++",
        "date_start":"2017-11-29T08:00",
        "date_end"  :"2017-11-29T10:00",
        "lecturer"  :"Cl&eacute;ment L",
        "location"  :"None::None@Room_000",
        "group"     :"All",
        "type"      :"TD",
        "year"      :"2",
        "tracks"    :"0x10",
        "comment"   :"Imported from .ics - Wed Sep 27 2017 09:17:03 GMT+0200 (CEST)"},
"C21020170927T071703113@import": {
        "ID"        :"C21020170927T071703113@import",
        "apogee"    :"4TBC901U",
        "acronym"   :"S09::POO++",
        "date_start":"2017-09-13T08:00",
        "date_end"  :"2017-09-13T10:00",
        "lecturer"  :"Cl&eacute;ment L",
        "location"  :"None::None@Room_000",
        "group"     :"All",
        "type"      :"TD",
        "year"      :"2",
        "tracks"    :"0x10",
        "comment"   :"Imported from .ics - Wed Sep 27 2017 09:17:03 GMT+0200 (CEST)"},
"C21020170927T071703114@import": {
        "ID"        :"C21020170927T071703114@import",
        "apogee"    :"4TBC901U",
        "acronym"   :"S09::POO++",
        "date_start":"2017-11-21T14:00",
        "date_end"  :"2017-11-21T16:00",
        "lecturer"  :"Cl&eacute;ment L",
        "location"  :"None::None@Room_000",
        "group"     :"All",
        "type"      :"Cours",
        "year"      :"2",
        "tracks"    :"0x10",
        "comment"   :"Imported from .ics - Wed Sep 27 2017 09:17:03 GMT+0200 (CEST)"},
"C21020170927T071703115@import": {
        "ID"        :"C21020170927T071703115@import",
        "apogee"    :"4TBC901U",
        "acronym"   :"S09::POO++",
        "date_start":"2017-11-14T14:00",
        "date_end"  :"2017-11-14T16:00",
        "lecturer"  :"Cl&eacute;ment L",
        "location"  :"None::None@Room_000",
        "group"     :"All",
        "type"      :"Cours",
        "year"      :"2",
        "tracks"    :"0x10",
        "comment"   :"Imported from .ics - Wed Sep 27 2017 09:17:03 GMT+0200 (CEST)"},
"C21020170927T071703116@import": {
        "ID"        :"C21020170927T071703116@import",
        "apogee"    :"4TBC901U",
        "acronym"   :"S09::POO++",
        "date_start":"2017-10-18T08:00",
        "date_end"  :"2017-10-18T10:00",
        "lecturer"  :"Cl&eacute;ment L",
        "location"  :"None::None@Room_000",
        "group"     :"All",
        "type"      :"TD",
        "year"      :"2",
        "tracks"    :"0x10",
        "comment"   :"Imported from .ics - Wed Sep 27 2017 09:17:03 GMT+0200 (CEST)"},
"C21020170927T071703117@import": {
        "ID"        :"C21020170927T071703117@import",
        "apogee"    :"4TBC901U",
        "acronym"   :"S09::POO++",
        "date_start":"2017-10-03T16:00",
        "date_end"  :"2017-10-03T18:00",
        "lecturer"  :"Cl&eacute;ment L",
        "location"  :"None::None@Room_000",
        "group"     :"All",
        "type"      :"TD",
        "year"      :"2",
        "tracks"    :"0x10",
        "comment"   :"Imported from .ics - Wed Sep 27 2017 09:17:03 GMT+0200 (CEST)"},
"C21020170927T071703118@import": {
        "ID"        :"C21020170927T071703118@import",
        "apogee"    :"4TBC901U",
        "acronym"   :"S09::POO++",
        "date_start":"2017-09-26T16:00",
        "date_end"  :"2017-09-26T18:00",
        "lecturer"  :"Cl&eacute;ment L",
        "location"  :"None::None@Room_000",
        "group"     :"All",
        "type"      :"TD",
        "year"      :"2",
        "tracks"    :"0x10",
        "comment"   :"Imported from .ics - Wed Sep 27 2017 09:17:03 GMT+0200 (CEST)"},
"C21020170927T071703119@import": {
        "ID"        :"C21020170927T071703119@import",
        "apogee"    :"4TBC901U",
        "acronym"   :"S09::POO++",
        "date_start":"2017-11-14T16:00",
        "date_end"  :"2017-11-14T18:00",
        "lecturer"  :"Cl&eacute;ment L",
        "location"  :"None::None@Room_000",
        "group"     :"All",
        "type"      :"TD",
        "year"      :"2",
        "tracks"    :"0x10",
        "comment"   :"Imported from .ics - Wed Sep 27 2017 09:17:03 GMT+0200 (CEST)"},
"C21020170927T071703120@import": {
        "ID"        :"C21020170927T071703120@import",
        "apogee"    :"4TBC901U",
        "acronym"   :"S09::POO++",
        "date_start":"2017-11-07T14:00",
        "date_end"  :"2017-11-07T16:00",
        "lecturer"  :"Cl&eacute;ment L",
        "location"  :"None::None@Room_000",
        "group"     :"All",
        "type"      :"Cours",
        "year"      :"2",
        "tracks"    :"0x10",
        "comment"   :"Imported from .ics - Wed Sep 27 2017 09:17:03 GMT+0200 (CEST)"},
"C21020170927T071703121@import": {
        "ID"        :"C21020170927T071703121@import",
        "apogee"    :"4TBC901U",
        "acronym"   :"S09::POO++",
        "date_start":"2017-11-07T16:00",
        "date_end"  :"2017-11-07T18:00",
        "lecturer"  :"Cl&eacute;ment L",
        "location"  :"None::None@Room_000",
        "group"     :"All",
        "type"      :"TD",
        "year"      :"2",
        "tracks"    :"0x10",
        "comment"   :"Imported from .ics - Wed Sep 27 2017 09:17:03 GMT+0200 (CEST)"},
"C21020170927T071703122@import": {
        "ID"        :"C21020170927T071703122@import",
        "apogee"    :"4TBC901U",
        "acronym"   :"S09::POO++",
        "date_start":"2017-09-12T14:00",
        "date_end"  :"2017-09-12T16:00",
        "lecturer"  :"Cl&eacute;ment L",
        "location"  :"None::None@Room_000",
        "group"     :"All",
        "type"      :"Cours",
        "year"      :"2",
        "tracks"    :"0x10",
        "comment"   :"Imported from .ics - Wed Sep 27 2017 09:17:03 GMT+0200 (CEST)"},
"C21020170927T071703123@import": {
        "ID"        :"C21020170927T071703123@import",
        "apogee"    :"4TBC901U",
        "acronym"   :"S09::POO++",
        "date_start":"2017-12-05T16:00",
        "date_end"  :"2017-12-05T18:00",
        "lecturer"  :"Cl&eacute;ment L",
        "location"  :"None::None@Room_000",
        "group"     :"All",
        "type"      :"TD",
        "year"      :"2",
        "tracks"    :"0x10",
        "comment"   :"Imported from .ics - Wed Sep 27 2017 09:17:03 GMT+0200 (CEST)"},
"C21020170927T071703124@import": {
        "ID"        :"C21020170927T071703124@import",
        "apogee"    :"4TBC901U",
        "acronym"   :"S09::POO++",
        "date_start":"2017-10-10T16:00",
        "date_end"  :"2017-10-10T18:00",
        "lecturer"  :"Cl&eacute;ment L",
        "location"  :"None::None@Room_000",
        "group"     :"All",
        "type"      :"TD",
        "year"      :"2",
        "tracks"    :"0x10",
        "comment"   :"Imported from .ics - Wed Sep 27 2017 09:17:03 GMT+0200 (CEST)"},
"C26020170927T071703125@import": {
        "ID"        :"C26020170927T071703125@import",
        "apogee"    :"4TBA903U",
        "acronym"   :"S09::QPG",
        "date_start":"2017-09-12T16:00",
        "date_end"  :"2017-09-12T18:00",
        "lecturer"  :"Schurdi-Levraud V",
        "location"  :"INRA::IBVM@Room_IBVM",
        "group"     :"All",
        "type"      :"Cours+TD",
        "year"      :"2",
        "tracks"    :"0x60",
        "comment"   :"Imported from .ics - Wed Sep 27 2017 09:17:03 GMT+0200 (CEST)"},
"C26020170927T071703126@import": {
        "ID"        :"C26020170927T071703126@import",
        "apogee"    :"4TBA903U",
        "acronym"   :"S09::QPG",
        "date_start":"2017-09-22T08:00",
        "date_end"  :"2017-09-22T10:00",
        "lecturer"  :"Schurdi-Levraud V",
        "location"  :"INRA::IBVM@Room_viro",
        "group"     :"All",
        "type"      :"Cours+TD",
        "year"      :"2",
        "tracks"    :"0x60",
        "comment"   :"Imported from .ics - Wed Sep 27 2017 09:17:03 GMT+0200 (CEST)"},
"C26020170927T071703127@import": {
        "ID"        :"C26020170927T071703127@import",
        "apogee"    :"4TBA903U",
        "acronym"   :"S09::QPG",
        "date_start":"2017-09-18T08:00",
        "date_end"  :"2017-09-18T12:00",
        "lecturer"  :"Schurdi-Levraud V",
        "location"  :"INRA::IBVM@Room_viro",
        "group"     :"All",
        "type"      :"Cours+TD",
        "year"      :"2",
        "tracks"    :"0x60",
        "comment"   :"Imported from .ics - Wed Sep 27 2017 09:17:03 GMT+0200 (CEST)"},
"C26020170927T071703128@import": {
        "ID"        :"C26020170927T071703128@import",
        "apogee"    :"4TBA903U",
        "acronym"   :"S09::QPG",
        "date_start":"2017-09-25T08:00",
        "date_end"  :"2017-09-25T12:00",
        "lecturer"  :"Schurdi-Levraud V",
        "location"  :"INRA::IBVM@Room_viro",
        "group"     :"All",
        "type"      :"Cours+TD",
        "year"      :"2",
        "tracks"    :"0x60",
        "comment"   :"Imported from .ics - Wed Sep 27 2017 09:17:03 GMT+0200 (CEST)"},
"C26020170927T071703129@import": {
        "ID"        :"C26020170927T071703129@import",
        "apogee"    :"4TBA903U",
        "acronym"   :"S09::QPG",
        "date_start":"2017-09-26T08:00",
        "date_end"  :"2017-09-26T18:00",
        "lecturer"  :"Schurdi-Levraud V",
        "location"  :"None::None@Room_000",
        "group"     :"All",
        "type"      :"Conference",
        "year"      :"2",
        "tracks"    :"0x60",
        "comment"   :"Imported from .ics - Wed Sep 27 2017 09:17:03 GMT+0200 (CEST)"},
"C26020170927T071703130@import": {
        "ID"        :"C26020170927T071703130@import",
        "apogee"    :"4TBA903U",
        "acronym"   :"S09::QPG",
        "date_start":"2017-10-02T08:00",
        "date_end"  :"2017-10-02T12:00",
        "lecturer"  :"Schurdi-Levraud V",
        "location"  :"INRA::IBVM@Room_viro",
        "group"     :"All",
        "type"      :"Cours+TD",
        "year"      :"2",
        "tracks"    :"0x60",
        "comment"   :"Imported from .ics - Wed Sep 27 2017 09:17:03 GMT+0200 (CEST)"},
"C26020170927T071703131@import": {
        "ID"        :"C26020170927T071703131@import",
        "apogee"    :"4TBA903U",
        "acronym"   :"S09::QPG",
        "date_start":"2017-10-09T08:00",
        "date_end"  :"2017-10-09T12:00",
        "lecturer"  :"Schurdi-Levraud V",
        "location"  :"INRA::IBVM@Room_viro",
        "group"     :"All",
        "type"      :"Cours+TD",
        "year"      :"2",
        "tracks"    :"0x60",
        "comment"   :"Imported from .ics - Wed Sep 27 2017 09:17:03 GMT+0200 (CEST)"},
"C26020170927T071703132@import": {
        "ID"        :"C26020170927T071703132@import",
        "apogee"    :"4TBA903U",
        "acronym"   :"S09::QPG",
        "date_start":"2017-10-11T14:00",
        "date_end"  :"2017-10-11T18:00",
        "lecturer"  :"Schurdi-Levraud V",
        "location"  :"INRA::IBVM@Room_viro",
        "group"     :"All",
        "type"      :"Cours+TD",
        "year"      :"2",
        "tracks"    :"0x60",
        "comment"   :"Imported from .ics - Wed Sep 27 2017 09:17:03 GMT+0200 (CEST)"},
"C26020170927T071703133@import": {
        "ID"        :"C26020170927T071703133@import",
        "apogee"    :"4TBA903U",
        "acronym"   :"S09::QPG",
        "date_start":"2017-10-16T08:00",
        "date_end"  :"2017-10-16T12:00",
        "lecturer"  :"Schurdi-Levraud V",
        "location"  :"INRA::IBVM@Room_viro",
        "group"     :"All",
        "type"      :"Cours+TD",
        "year"      :"2",
        "tracks"    :"0x60",
        "comment"   :"Imported from .ics - Wed Sep 27 2017 09:17:03 GMT+0200 (CEST)"},
"C26020170927T071703134@import": {
        "ID"        :"C26020170927T071703134@import",
        "apogee"    :"4TBA903U",
        "acronym"   :"S09::QPG",
        "date_start":"2017-11-06T08:00",
        "date_end"  :"2017-11-06T12:00",
        "lecturer"  :"Schurdi-Levraud V",
        "location"  :"INRA::IBVM@Room_viro",
        "group"     :"All",
        "type"      :"Cours+TD",
        "year"      :"2",
        "tracks"    :"0x60",
        "comment"   :"Imported from .ics - Wed Sep 27 2017 09:17:03 GMT+0200 (CEST)"},
"C26020170927T071703135@import": {
        "ID"        :"C26020170927T071703135@import",
        "apogee"    :"4TBA903U",
        "acronym"   :"S09::QPG",
        "date_start":"2017-11-07T14:00",
        "date_end"  :"2017-11-07T18:00",
        "lecturer"  :"Schurdi-Levraud V",
        "location"  :"INRA::IBVM@Room_viro",
        "group"     :"All",
        "type"      :"Cours+TD",
        "year"      :"2",
        "tracks"    :"0x60",
        "comment"   :"Imported from .ics - Wed Sep 27 2017 09:17:03 GMT+0200 (CEST)"},
"C26020170927T071703136@import": {
        "ID"        :"C26020170927T071703136@import",
        "apogee"    :"4TBA903U",
        "acronym"   :"S09::QPG",
        "date_start":"2017-11-13T08:00",
        "date_end"  :"2017-11-13T12:00",
        "lecturer"  :"Schurdi-Levraud V",
        "location"  :"INRA::IBVM@Room_viro",
        "group"     :"All",
        "type"      :"Cours+TD",
        "year"      :"2",
        "tracks"    :"0x60",
        "comment"   :"Imported from .ics - Wed Sep 27 2017 09:17:03 GMT+0200 (CEST)"},
"C26020170927T071703137@import": {
        "ID"        :"C26020170927T071703137@import",
        "apogee"    :"4TBA903U",
        "acronym"   :"S09::QPG",
        "date_start":"2017-11-20T08:00",
        "date_end"  :"2017-11-20T12:00",
        "lecturer"  :"Schurdi-Levraud V",
        "location"  :"INRA::IBVM@Room_viro",
        "group"     :"All",
        "type"      :"Cours+TD",
        "year"      :"2",
        "tracks"    :"0x60",
        "comment"   :"Imported from .ics - Wed Sep 27 2017 09:17:03 GMT+0200 (CEST)"},
"C26020170927T071703138@import": {
        "ID"        :"C26020170927T071703138@import",
        "apogee"    :"4TBA903U",
        "acronym"   :"S09::QPG",
        "date_start":"2017-11-27T08:00",
        "date_end"  :"2017-11-27T12:00",
        "lecturer"  :"Schurdi-Levraud V",
        "location"  :"INRA::IBVM@Room_viro",
        "group"     :"All",
        "type"      :"Cours+TD",
        "year"      :"2",
        "tracks"    :"0x60",
        "comment"   :"Imported from .ics - Wed Sep 27 2017 09:17:03 GMT+0200 (CEST)"},
"C26020170927T071703139@import": {
        "ID"        :"C26020170927T071703139@import",
        "apogee"    :"4TBA903U",
        "acronym"   :"S09::QPG",
        "date_start":"2017-11-30T08:00",
        "date_end"  :"2017-11-30T12:00",
        "lecturer"  :"Schurdi-Levraud V",
        "location"  :"INRA::IBVM@Room_viro",
        "group"     :"All",
        "type"      :"Cours+TD",
        "year"      :"2",
        "tracks"    :"0x60",
        "comment"   :"Imported from .ics - Wed Sep 27 2017 09:17:03 GMT+0200 (CEST)"},
"C26020170927T071703140@import": {
        "ID"        :"C26020170927T071703140@import",
        "apogee"    :"4TBA903U",
        "acronym"   :"S09::QPG",
        "date_start":"2017-12-04T08:00",
        "date_end"  :"2017-12-04T12:00",
        "lecturer"  :"Schurdi-Levraud V",
        "location"  :"INRA::IBVM@Room_mollicutes",
        "group"     :"All",
        "type"      :"Cours+TD",
        "year"      :"2",
        "tracks"    :"0x60",
        "comment"   :"Imported from .ics - Wed Sep 27 2017 09:17:03 GMT+0200 (CEST)"},
"C26020170927T071703141@import": {
        "ID"        :"C26020170927T071703141@import",
        "apogee"    :"4TDE901U",
        "acronym"   :"S09::SIG",
        "date_start":"2018-01-09T10:00",
        "date_end"  :"2018-01-09T12:00",
        "lecturer"  :"Bujan S",
        "location"  :"None::None@Room_000",
        "group"     :"All",
        "type"      :"Cours+TD",
        "year"      :"2",
        "tracks"    :"0x60",
        "comment"   :"Imported from .ics - Wed Sep 27 2017 09:17:03 GMT+0200 (CEST)"},
"C26020170927T071703142@import": {
        "ID"        :"C26020170927T071703142@import",
        "apogee"    :"4TDE901U",
        "acronym"   :"S09::SIG",
        "date_start":"2018-01-18T14:00",
        "date_end"  :"2018-01-18T17:00",
        "lecturer"  :"Zaragosi S",
        "location"  :"None::None@Room_000",
        "group"     :"All",
        "type"      :"PROJET",
        "year"      :"2",
        "tracks"    :"0x60",
        "comment"   :"Imported from .ics - Wed Sep 27 2017 09:17:03 GMT+0200 (CEST)"},
"C26020170927T071703143@import": {
        "ID"        :"C26020170927T071703143@import",
        "apogee"    :"4TDE901U",
        "acronym"   :"S09::SIG",
        "date_start":"2018-01-12T14:00",
        "date_end"  :"2018-01-12T17:00",
        "lecturer"  :"Zaragosi S",
        "location"  :"None::None@Room_000",
        "group"     :"All",
        "type"      :"Cours+TD",
        "year"      :"2",
        "tracks"    :"0x60",
        "comment"   :"Imported from .ics - Wed Sep 27 2017 09:17:03 GMT+0200 (CEST)"},
"C26020170927T071703144@import": {
        "ID"        :"C26020170927T071703144@import",
        "apogee"    :"4TDE901U",
        "acronym"   :"S09::SIG",
        "date_start":"2018-01-19T14:00",
        "date_end"  :"2018-01-19T17:00",
        "lecturer"  :"Zaragosi S",
        "location"  :"None::None@Room_000",
        "group"     :"All",
        "type"      :"PROJET",
        "year"      :"2",
        "tracks"    :"0x60",
        "comment"   :"Imported from .ics - Wed Sep 27 2017 09:17:03 GMT+0200 (CEST)"},
"C26020170927T071703145@import": {
        "ID"        :"C26020170927T071703145@import",
        "apogee"    :"4TDE901U",
        "acronym"   :"S09::SIG",
        "date_start":"2018-01-08T09:00",
        "date_end"  :"2018-01-08T12:00",
        "lecturer"  :"Zaragosi S",
        "location"  :"None::None@Room_000",
        "group"     :"All",
        "type"      :"Cours+TD",
        "year"      :"2",
        "tracks"    :"0x60",
        "comment"   :"Imported from .ics - Wed Sep 27 2017 09:17:03 GMT+0200 (CEST)"},
"C26020170927T071703146@import": {
        "ID"        :"C26020170927T071703146@import",
        "apogee"    :"4TDE901U",
        "acronym"   :"S09::SIG",
        "date_start":"2018-01-09T14:00",
        "date_end"  :"2018-01-09T17:00",
        "lecturer"  :"Hanquiez V",
        "location"  :"None::None@Room_000",
        "group"     :"All",
        "type"      :"Cours+TD",
        "year"      :"2",
        "tracks"    :"0x60",
        "comment"   :"Imported from .ics - Wed Sep 27 2017 09:17:03 GMT+0200 (CEST)"},
"C26020170927T071703147@import": {
        "ID"        :"C26020170927T071703147@import",
        "apogee"    :"4TDE901U",
        "acronym"   :"S09::SIG",
        "date_start":"2018-01-11T14:00",
        "date_end"  :"2018-01-11T17:00",
        "lecturer"  :"Cochard D",
        "location"  :"None::None@Room_000",
        "group"     :"All",
        "type"      :"Cours+TD",
        "year"      :"2",
        "tracks"    :"0x60",
        "comment"   :"Imported from .ics - Wed Sep 27 2017 09:17:03 GMT+0200 (CEST)"},
"C26020170927T071703148@import": {
        "ID"        :"C26020170927T071703148@import",
        "apogee"    :"4TDE901U",
        "acronym"   :"S09::SIG",
        "date_start":"2018-01-17T14:00",
        "date_end"  :"2018-01-17T17:00",
        "lecturer"  :"Zaragosi S",
        "location"  :"None::None@Room_000",
        "group"     :"All",
        "type"      :"PROJET",
        "year"      :"2",
        "tracks"    :"0x60",
        "comment"   :"Imported from .ics - Wed Sep 27 2017 09:17:03 GMT+0200 (CEST)"},
"C26020170927T071703149@import": {
        "ID"        :"C26020170927T071703149@import",
        "apogee"    :"4TDE901U",
        "acronym"   :"S09::SIG",
        "date_start":"2018-01-10T09:00",
        "date_end"  :"2018-01-10T12:00",
        "lecturer"  :"Zaragosi S",
        "location"  :"None::None@Room_000",
        "group"     :"All",
        "type"      :"Cours+TD",
        "year"      :"2",
        "tracks"    :"0x60",
        "comment"   :"Imported from .ics - Wed Sep 27 2017 09:17:03 GMT+0200 (CEST)"},
"C26020170927T071703150@import": {
        "ID"        :"C26020170927T071703150@import",
        "apogee"    :"4TDE901U",
        "acronym"   :"S09::SIG",
        "date_start":"2018-01-09T09:00",
        "date_end"  :"2018-01-09T10:00",
        "lecturer"  :"Normandin C",
        "location"  :"None::None@Room_000",
        "group"     :"All",
        "type"      :"Cours+TD",
        "year"      :"2",
        "tracks"    :"0x60",
        "comment"   :"Imported from .ics - Wed Sep 27 2017 09:17:03 GMT+0200 (CEST)"},
"C26020170927T071703151@import": {
        "ID"        :"C26020170927T071703151@import",
        "apogee"    :"4TDE901U",
        "acronym"   :"S09::SIG",
        "date_start":"2018-01-15T14:00",
        "date_end"  :"2018-01-15T17:00",
        "lecturer"  :"Zaragosi S",
        "location"  :"None::None@Room_000",
        "group"     :"All",
        "type"      :"PROJET",
        "year"      :"2",
        "tracks"    :"0x60",
        "comment"   :"Imported from .ics - Wed Sep 27 2017 09:17:03 GMT+0200 (CEST)"},
"C26020170927T071703152@import": {
        "ID"        :"C26020170927T071703152@import",
        "apogee"    :"4TDE901U",
        "acronym"   :"S09::SIG",
        "date_start":"2018-01-18T09:00",
        "date_end"  :"2018-01-18T12:00",
        "lecturer"  :"Zaragosi S",
        "location"  :"None::None@Room_000",
        "group"     :"All",
        "type"      :"PROJET",
        "year"      :"2",
        "tracks"    :"0x60",
        "comment"   :"Imported from .ics - Wed Sep 27 2017 09:17:03 GMT+0200 (CEST)"},
"C26020170927T071703153@import": {
        "ID"        :"C26020170927T071703153@import",
        "apogee"    :"4TDE901U",
        "acronym"   :"S09::SIG",
        "date_start":"2018-01-08T14:00",
        "date_end"  :"2018-01-08T17:00",
        "lecturer"  :"Hanquiez V",
        "location"  :"None::None@Room_000",
        "group"     :"All",
        "type"      :"Cours+TD",
        "year"      :"2",
        "tracks"    :"0x60",
        "comment"   :"Imported from .ics - Wed Sep 27 2017 09:17:03 GMT+0200 (CEST)"},
"C26020170927T071703154@import": {
        "ID"        :"C26020170927T071703154@import",
        "apogee"    :"4TDE901U",
        "acronym"   :"S09::SIG",
        "date_start":"2018-01-16T09:00",
        "date_end"  :"2018-01-16T12:00",
        "lecturer"  :"Zaragosi S",
        "location"  :"None::None@Room_000",
        "group"     :"All",
        "type"      :"PROJET",
        "year"      :"2",
        "tracks"    :"0x60",
        "comment"   :"Imported from .ics - Wed Sep 27 2017 09:17:03 GMT+0200 (CEST)"},
"C26020170927T071703155@import": {
        "ID"        :"C26020170927T071703155@import",
        "apogee"    :"4TDE901U",
        "acronym"   :"S09::SIG",
        "date_start":"2018-01-17T09:00",
        "date_end"  :"2018-01-17T12:00",
        "lecturer"  :"Zaragosi S",
        "location"  :"None::None@Room_000",
        "group"     :"All",
        "type"      :"PROJET",
        "year"      :"2",
        "tracks"    :"0x60",
        "comment"   :"Imported from .ics - Wed Sep 27 2017 09:17:03 GMT+0200 (CEST)"},
"C26020170927T071703156@import": {
        "ID"        :"C26020170927T071703156@import",
        "apogee"    :"4TDE901U",
        "acronym"   :"S09::SIG",
        "date_start":"2018-01-12T09:00",
        "date_end"  :"2018-01-12T12:00",
        "lecturer"  :"Zaragosi S",
        "location"  :"None::None@Room_000",
        "group"     :"All",
        "type"      :"Cours+TD",
        "year"      :"2",
        "tracks"    :"0x60",
        "comment"   :"Imported from .ics - Wed Sep 27 2017 09:17:03 GMT+0200 (CEST)"},
"C26020170927T071703157@import": {
        "ID"        :"C26020170927T071703157@import",
        "apogee"    :"4TDE901U",
        "acronym"   :"S09::SIG",
        "date_start":"2018-01-19T09:00",
        "date_end"  :"2018-01-19T12:00",
        "lecturer"  :"Zaragosi S",
        "location"  :"None::None@Room_000",
        "group"     :"All",
        "type"      :"PROJET",
        "year"      :"2",
        "tracks"    :"0x60",
        "comment"   :"Imported from .ics - Wed Sep 27 2017 09:17:03 GMT+0200 (CEST)"},
"C26020170927T071703158@import": {
        "ID"        :"C26020170927T071703158@import",
        "apogee"    :"4TDE901U",
        "acronym"   :"S09::SIG",
        "date_start":"2018-01-10T14:00",
        "date_end"  :"2018-01-10T17:00",
        "lecturer"  :"Zaragosi S",
        "location"  :"None::None@Room_000",
        "group"     :"All",
        "type"      :"Cours+TD",
        "year"      :"2",
        "tracks"    :"0x60",
        "comment"   :"Imported from .ics - Wed Sep 27 2017 09:17:03 GMT+0200 (CEST)"},
"C26020170927T071703159@import": {
        "ID"        :"C26020170927T071703159@import",
        "apogee"    :"4TDE901U",
        "acronym"   :"S09::SIG",
        "date_start":"2018-01-16T14:00",
        "date_end"  :"2018-01-16T17:00",
        "lecturer"  :"Zaragosi S",
        "location"  :"None::None@Room_000",
        "group"     :"All",
        "type"      :"PROJET",
        "year"      :"2",
        "tracks"    :"0x60",
        "comment"   :"Imported from .ics - Wed Sep 27 2017 09:17:03 GMT+0200 (CEST)"},
"C26020170927T071703160@import": {
        "ID"        :"C26020170927T071703160@import",
        "apogee"    :"4TDE901U",
        "acronym"   :"S09::SIG",
        "date_start":"2018-01-15T09:00",
        "date_end"  :"2018-01-15T12:00",
        "lecturer"  :"Zaragosi S",
        "location"  :"None::None@Room_000",
        "group"     :"All",
        "type"      :"PROJET",
        "year"      :"2",
        "tracks"    :"0x60",
        "comment"   :"Imported from .ics - Wed Sep 27 2017 09:17:03 GMT+0200 (CEST)"},
"C26020170927T071703161@import": {
        "ID"        :"C26020170927T071703161@import",
        "apogee"    :"4TDE901U",
        "acronym"   :"S09::SIG",
        "date_start":"2018-01-11T09:00",
        "date_end"  :"2018-01-11T12:00",
        "lecturer"  :"Cochard D",
        "location"  :"None::None@Room_000",
        "group"     :"All",
        "type"      :"Cours+TD",
        "year"      :"2",
        "tracks"    :"0x60",
        "comment"   :"Imported from .ics - Wed Sep 27 2017 09:17:03 GMT+0200 (CEST)"},
"C26120170927T071703162@import": {
        "ID"        :"C26120170927T071703162@import",
        "apogee"    :"4TBI901U",
        "acronym"   :"S09::StrubiGL",
        "date_start":"2017-09-07T09:00",
        "date_end"  :"2017-09-07T11:00",
        "lecturer"  :"Taveau JC",
        "location"  :"Talence::A22@Room_119",
        "group"     :"All",
        "type"      :"Cours",
        "year"      :"2",
        "tracks"    :"0x61",
        "comment"   :"Imported from .ics - Wed Sep 27 2017 09:17:03 GMT+0200 (CEST)"},
"C26120170927T071703163@import": {
        "ID"        :"C26120170927T071703163@import",
        "apogee"    :"4TBI901U",
        "acronym"   :"S09::StrubiGL",
        "date_start":"2017-11-09T14:00",
        "date_end"  :"2017-11-09T18:00",
        "lecturer"  :"taveau",
        "location"  :"Talence::A29-CREMI@Room_000",
        "group"     :"All",
        "type"      :"TD machine",
        "year"      :"2",
        "tracks"    :"0x61",
        "comment"   :"Imported from .ics - Wed Sep 27 2017 09:17:03 GMT+0200 (CEST)"},
"C26120170927T071703164@import": {
        "ID"        :"C26120170927T071703164@import",
        "apogee"    :"4TBI901U",
        "acronym"   :"S09::StrubiGL",
        "date_start":"2017-11-14T09:00",
        "date_end"  :"2017-11-14T12:00",
        "lecturer"  :"Taveau JC",
        "location"  :"None::None@Room_000",
        "group"     :"All",
        "type"      :"Cours",
        "year"      :"2",
        "tracks"    :"0x61",
        "comment"   :"Imported from .ics - Wed Sep 27 2017 09:17:03 GMT+0200 (CEST)"},
"C26120170927T071703165@import": {
        "ID"        :"C26120170927T071703165@import",
        "apogee"    :"4TBI901U",
        "acronym"   :"S09::StrubiGL",
        "date_start":"2017-11-09T14:00",
        "date_end"  :"2017-11-09T18:00",
        "lecturer"  :"taveau",
        "location"  :"Talence::A29-CREMI@Room_101",
        "group"     :"All",
        "type"      :"TD machine",
        "year"      :"2",
        "tracks"    :"0x61",
        "comment"   :"Imported from .ics - Wed Sep 27 2017 09:17:03 GMT+0200 (CEST)"},
"C26120170927T071703166@import": {
        "ID"        :"C26120170927T071703166@import",
        "apogee"    :"4TBI901U",
        "acronym"   :"S09::StrubiGL",
        "date_start":"2017-12-07T14:00",
        "date_end"  :"2017-12-07T18:00",
        "lecturer"  :"taveau",
        "location"  :"Talence::A29-CREMI@Room_203",
        "group"     :"All",
        "type"      :"TD machine",
        "year"      :"2",
        "tracks"    :"0x61",
        "comment"   :"Imported from .ics - Wed Sep 27 2017 09:17:03 GMT+0200 (CEST)"},
"C26120170927T071703167@import": {
        "ID"        :"C26120170927T071703167@import",
        "apogee"    :"4TBI901U",
        "acronym"   :"S09::StrubiGL",
        "date_start":"2017-12-14T14:00",
        "date_end"  :"2017-12-14T18:00",
        "lecturer"  :"taveau",
        "location"  :"Talence::A29-CREMI@Room_203",
        "group"     :"All",
        "type"      :"TD machine",
        "year"      :"2",
        "tracks"    :"0x61",
        "comment"   :"Imported from .ics - Wed Sep 27 2017 09:17:03 GMT+0200 (CEST)"},
"C26120170927T071703168@import": {
        "ID"        :"C26120170927T071703168@import",
        "apogee"    :"4TBI901U",
        "acronym"   :"S09::StrubiGL",
        "date_start":"2017-11-28T08:00",
        "date_end"  :"2017-11-28T12:00",
        "lecturer"  :"Taveau JC",
        "location"  :"None::None@Room_000",
        "group"     :"All",
        "type"      :"Cours+TD",
        "year"      :"2",
        "tracks"    :"0x61",
        "comment"   :"Imported from .ics - Wed Sep 27 2017 09:17:03 GMT+0200 (CEST)"},
"C26120170927T071703169@import": {
        "ID"        :"C26120170927T071703169@import",
        "apogee"    :"4TBI901U",
        "acronym"   :"S09::StrubiGL",
        "date_start":"2017-11-23T08:00",
        "date_end"  :"2017-11-23T12:00",
        "lecturer"  :"Taveau JC",
        "location"  :"Talence::A29-CREMI@Room_205",
        "group"     :"All",
        "type"      :"Cours+TD",
        "year"      :"2",
        "tracks"    :"0x61",
        "comment"   :"Imported from .ics - Wed Sep 27 2017 09:17:03 GMT+0200 (CEST)"},
"C26120170927T071703170@import": {
        "ID"        :"C26120170927T071703170@import",
        "apogee"    :"4TBI901U",
        "acronym"   :"S09::StrubiGL",
        "date_start":"2017-11-07T10:00",
        "date_end"  :"2017-11-07T12:00",
        "lecturer"  :"Taveau JC",
        "location"  :"Talence::B7@Room_007",
        "group"     :"All",
        "type"      :"Cours",
        "year"      :"2",
        "tracks"    :"0x61",
        "comment"   :"Imported from .ics - Wed Sep 27 2017 09:17:03 GMT+0200 (CEST)"},
"C26120170927T071703171@import": {
        "ID"        :"C26120170927T071703171@import",
        "apogee"    :"4TBI901U",
        "acronym"   :"S09::StrubiGL",
        "date_start":"2017-10-12T14:00",
        "date_end"  :"2017-10-12T16:00",
        "lecturer"  :"Taveau JC",
        "location"  :"Talence::B5@Amphi_GABA",
        "group"     :"All",
        "type"      :"Cours",
        "year"      :"2",
        "tracks"    :"0x61",
        "comment"   :"Imported from .ics - Wed Sep 27 2017 09:17:03 GMT+0200 (CEST)"},
"C26120170927T071703172@import": {
        "ID"        :"C26120170927T071703172@import",
        "apogee"    :"4TBI901U",
        "acronym"   :"S09::StrubiGL",
        "date_start":"2017-10-05T14:00",
        "date_end"  :"2017-10-05T16:00",
        "lecturer"  :"Taveau JC",
        "location"  :"Talence::B5@Amphi_GABA",
        "group"     :"All",
        "type"      :"Cours",
        "year"      :"2",
        "tracks"    :"0x61",
        "comment"   :"Imported from .ics - Wed Sep 27 2017 09:17:03 GMT+0200 (CEST)"},
"C26120170927T071703173@import": {
        "ID"        :"C26120170927T071703173@import",
        "apogee"    :"4TBI901U",
        "acronym"   :"S09::StrubiGL",
        "date_start":"2017-10-17T10:00",
        "date_end"  :"2017-10-17T12:00",
        "lecturer"  :"Taveau JC",
        "location"  :"Talence::B7@Room_004",
        "group"     :"All",
        "type"      :"Cours",
        "year"      :"2",
        "tracks"    :"0x61",
        "comment"   :"Imported from .ics - Wed Sep 27 2017 09:17:03 GMT+0200 (CEST)"},
"C27020170927T071703174@import": {
        "ID"        :"C27020170927T071703174@import",
        "apogee"    :"4TBE901U",
        "acronym"   :"S09::TDE++",
        "date_start":"2017-09-29T09:00",
        "date_end"  :"2017-09-29T13:00",
        "lecturer"  :"David V",
        "location"  :"Talence::None@Room_000",
        "group"     :"All",
        "type"      :"TD machine",
        "year"      :"2",
        "tracks"    :"0x70",
        "comment"   :"Imported from .ics - Wed Sep 27 2017 09:17:03 GMT+0200 (CEST)"},
"C27020170927T071703175@import": {
        "ID"        :"C27020170927T071703175@import",
        "apogee"    :"4TBE901U",
        "acronym"   :"S09::TDE++",
        "date_start":"2017-09-20T09:00",
        "date_end"  :"2017-09-20T12:00",
        "lecturer"  :"Drouineau H",
        "location"  :"Talence::B5@Room_001",
        "group"     :"All",
        "type"      :"TD machine",
        "year"      :"2",
        "tracks"    :"0x70",
        "comment"   :"Imported from .ics - Wed Sep 27 2017 09:17:03 GMT+0200 (CEST)"},
"C27020170927T071703176@import": {
        "ID"        :"C27020170927T071703176@import",
        "apogee"    :"4TBE901U",
        "acronym"   :"S09::TDE++",
        "date_start":"2017-09-20T14:00",
        "date_end"  :"2017-09-20T18:00",
        "lecturer"  :"David V",
        "location"  :"Talence::B5@Room_002",
        "group"     :"All",
        "type"      :"TD machine",
        "year"      :"2",
        "tracks"    :"0x70",
        "comment"   :"Imported from .ics - Wed Sep 27 2017 09:17:03 GMT+0200 (CEST)"},
"C27020170927T071703177@import": {
        "ID"        :"C27020170927T071703177@import",
        "apogee"    :"4TBE901U",
        "acronym"   :"S09::TDE++",
        "date_start":"2017-09-08T09:00",
        "date_end"  :"2017-09-08T10:00",
        "lecturer"  :"David V",
        "location"  :"Talence::A30-LaBRI@Room_073",
        "group"     :"All",
        "type"      :"Cours",
        "year"      :"2",
        "tracks"    :"0x70",
        "comment"   :"Imported from .ics - Wed Sep 27 2017 09:17:03 GMT+0200 (CEST)"},
"C27020170927T071703178@import": {
        "ID"        :"C27020170927T071703178@import",
        "apogee"    :"4TBE901U",
        "acronym"   :"S09::TDE++",
        "date_start":"2017-09-18T09:00",
        "date_end"  :"2017-09-18T12:00",
        "lecturer"  :"Benot ML",
        "location"  :"Talence::B5@Amphi_GABA",
        "group"     :"All",
        "type"      :"Cours",
        "year"      :"2",
        "tracks"    :"0x70",
        "comment"   :"Imported from .ics - Wed Sep 27 2017 09:17:03 GMT+0200 (CEST)"},
"C27020170927T071703179@import": {
        "ID"        :"C27020170927T071703179@import",
        "apogee"    :"4TBE901U",
        "acronym"   :"S09::TDE++",
        "date_start":"2017-09-18T14:00",
        "date_end"  :"2017-09-18T17:00",
        "lecturer"  :"Benot ML",
        "location"  :"Talence::B5@Amphi_GABA",
        "group"     :"All",
        "type"      :"Cours",
        "year"      :"2",
        "tracks"    :"0x70",
        "comment"   :"Imported from .ics - Wed Sep 27 2017 09:17:03 GMT+0200 (CEST)"},
"C27020170927T071703180@import": {
        "ID"        :"C27020170927T071703180@import",
        "apogee"    :"4TBE901U",
        "acronym"   :"S09::TDE++",
        "date_start":"2017-09-19T09:00",
        "date_end"  :"2017-09-19T12:00",
        "lecturer"  :"Drouineau H",
        "location"  :"Talence::B18@Amphi_B18",
        "group"     :"All",
        "type"      :"Cours",
        "year"      :"2",
        "tracks"    :"0x70",
        "comment"   :"Imported from .ics - Wed Sep 27 2017 09:17:03 GMT+0200 (CEST)"},
"C27020170927T071703181@import": {
        "ID"        :"C27020170927T071703181@import",
        "apogee"    :"4TBE901U",
        "acronym"   :"S09::TDE++",
        "date_start":"2017-09-19T14:00",
        "date_end"  :"2017-09-19T16:00",
        "lecturer"  :"David V",
        "location"  :"Talence::B7@Room_003",
        "group"     :"All",
        "type"      :"TD",
        "year"      :"2",
        "tracks"    :"0x70",
        "comment"   :"Imported from .ics - Wed Sep 27 2017 09:17:03 GMT+0200 (CEST)"},
"C27020170927T071703182@import": {
        "ID"        :"C27020170927T071703182@import",
        "apogee"    :"4TBE901U",
        "acronym"   :"S09::TDE++",
        "date_start":"2017-09-21T14:00",
        "date_end"  :"2017-09-21T16:00",
        "lecturer"  :"David V",
        "location"  :"Talence::B7@Room_003",
        "group"     :"All",
        "type"      :"TD",
        "year"      :"2",
        "tracks"    :"0x70",
        "comment"   :"Imported from .ics - Wed Sep 27 2017 09:17:03 GMT+0200 (CEST)"},
"C27020170927T071703183@import": {
        "ID"        :"C27020170927T071703183@import",
        "apogee"    :"4TBE901U",
        "acronym"   :"S09::TDE++",
        "date_start":"2017-09-22T09:00",
        "date_end"  :"2017-09-22T12:00",
        "lecturer"  :"Gr&eacute;mare A",
        "location"  :"Talence::B5@Amphi_GABA",
        "group"     :"All",
        "type"      :"Cours",
        "year"      :"2",
        "tracks"    :"0x70",
        "comment"   :"Imported from .ics - Wed Sep 27 2017 09:17:03 GMT+0200 (CEST)"},
"C27020170927T071703184@import": {
        "ID"        :"C27020170927T071703184@import",
        "apogee"    :"4TBE901U",
        "acronym"   :"S09::TDE++",
        "date_start":"2017-09-22T16:00",
        "date_end"  :"2017-09-22T19:00",
        "lecturer"  :"David V",
        "location"  :"Talence::B5@Room_002",
        "group"     :"All",
        "type"      :"TD machine",
        "year"      :"2",
        "tracks"    :"0x70",
        "comment"   :"Imported from .ics - Wed Sep 27 2017 09:17:03 GMT+0200 (CEST)"},
"C27020170927T071703185@import": {
        "ID"        :"C27020170927T071703185@import",
        "apogee"    :"4TBE901U",
        "acronym"   :"S09::TDE++",
        "date_start":"2017-09-25T09:00",
        "date_end"  :"2017-09-25T12:00",
        "lecturer"  :"Benot ML",
        "location"  :"Talence::B5@Amphi_GABA",
        "group"     :"All",
        "type"      :"Cours",
        "year"      :"2",
        "tracks"    :"0x70",
        "comment"   :"Imported from .ics - Wed Sep 27 2017 09:17:03 GMT+0200 (CEST)"},
"C27020170927T071703186@import": {
        "ID"        :"C27020170927T071703186@import",
        "apogee"    :"4TBE901U",
        "acronym"   :"S09::TDE++",
        "date_start":"2017-09-26T14:00",
        "date_end"  :"2017-09-26T17:00",
        "lecturer"  :"Gr&eacute;mare A",
        "location"  :"Talence::B5@Room_001",
        "group"     :"All",
        "type"      :"TD machine",
        "year"      :"2",
        "tracks"    :"0x70",
        "comment"   :"Imported from .ics - Wed Sep 27 2017 09:17:03 GMT+0200 (CEST)"},
"C27020170927T071703187@import": {
        "ID"        :"C27020170927T071703187@import",
        "apogee"    :"4TBE901U",
        "acronym"   :"S09::TDE++",
        "date_start":"2017-09-27T09:00",
        "date_end"  :"2017-09-27T12:00",
        "lecturer"  :"Benot ML",
        "location"  :"Talence::B5@Room_002",
        "group"     :"All",
        "type"      :"TD machine",
        "year"      :"2",
        "tracks"    :"0x70",
        "comment"   :"Imported from .ics - Wed Sep 27 2017 09:17:03 GMT+0200 (CEST)"},
"C27020170927T071703188@import": {
        "ID"        :"C27020170927T071703188@import",
        "apogee"    :"4TBE901U",
        "acronym"   :"S09::TDE++",
        "date_start":"2017-09-27T16:00",
        "date_end"  :"2017-09-27T19:00",
        "lecturer"  :"David V",
        "location"  :"Talence::B5@Room_001",
        "group"     :"All",
        "type"      :"TD machine",
        "year"      :"2",
        "tracks"    :"0x70",
        "comment"   :"Imported from .ics - Wed Sep 27 2017 09:17:03 GMT+0200 (CEST)"},
"C27020170927T071703189@import": {
        "ID"        :"C27020170927T071703189@import",
        "apogee"    :"4TBE901U",
        "acronym"   :"S09::TDE++",
        "date_start":"2017-09-28T09:00",
        "date_end"  :"2017-09-28T12:00",
        "lecturer"  :"Benot ML",
        "location"  :"Talence::B5@Room_000",
        "group"     :"All",
        "type"      :"TD machine",
        "year"      :"2",
        "tracks"    :"0x70",
        "comment"   :"Imported from .ics - Wed Sep 27 2017 09:17:03 GMT+0200 (CEST)"}
}
